Sesión 2/NOR/nor2.vhd
--puerta and de 2 entradas

ENTITY nor2 IS
	GENERIC (retardo: TIME:= 2 ns);
	PORT (e1, e2: IN BIT; sal: OUT BIT);
END nor2;

ARCHITECTURE comportamiento OF nor2 IS
BEGIN
	PROCESS (e1, e2)
	BEGIN
		sal <= e1 NOR e2 AFTER retardo;
	END PROCESS;
END comportamiento;

Sesión 0/NOR/tb_nor2.vhd
ENTITY tb_nor2 IS
END tb_nor2;

ARCHITECTURE estructural OF tb_nor2 IS

	COMPONENT nor2
		PORT (e1, e2: IN BIT; sal: OUT BIT);
	END COMPONENT;
	

	FOR componente: nor2 USE ENTITY WORK.nor2(comportamiento);


	SIGNAL a, b: BIT:='0';
	SIGNAL s: BIT:='0';


BEGIN

	componente: nor2 PORT MAP (a, b, s);
	
	
	PROCESS
	BEGIN
		a<= '0';
		b<= '0';
		WAIT FOR 5 ns;
		a<= '1';
		b<= '0';
		WAIT FOR 5 ns;
		a<= '0';
		b<= '1';
		WAIT FOR 5 ns;
		a<= '1';
		b<= '1';
		WAIT FOR 5 ns;
		WAIT;
	END PROCESS;
END estructural;

Sesión 0/NOR/cronograma.vcd
$date
  Tue Oct 13 17:40:06 2020
$end
$version
  GHDL v0
$end
$timescale
  1 fs
$end
$scope module standard $end
$upscope $end
$scope module tb_nor2 $end
$var reg 1 ! a $end
$var reg 1 " b $end
$var reg 1 # s $end
$scope module componente $end
$var reg 1 $ e1 $end
$var reg 1 % e2 $end
$var reg 1 & sal $end
$upscope $end
$upscope $end
$enddefinitions $end
#0
0!
0"
0#
0$
0%
0&
#1000000
1#
1&
#5000000
1!
1$
#6000000
0#
0&
#10000000
0!
1"
0$
1%
#11000000
0&
#15000000
1!
1$
#16000000
0&
