Sesión 8/or2.vhd
ENTITY or2 IS
	GENERIC (retardo: TIME:= 1 ns);
	PORT (e1, e2: IN BIT; sal: OUT BIT);
END or2;

ARCHITECTURE comportamiento OF or2 IS
BEGIN
	PROCESS (e1, e2)
	BEGIN
		sal <= e1 OR e2 AFTER retardo;
	END PROCESS;
END comportamiento;

Sesión 7/Primer '0'/and2.vhd
ENTITY and2 IS
	GENERIC (retardo: TIME:= 1 ns);
	PORT (e1, e2: IN BIT; sal: OUT BIT);
END and2;

ARCHITECTURE comportamiento OF and2 IS
BEGIN
	PROCESS (e1, e2)
	BEGIN
		sal <= e1 AND e2 AFTER retardo;
	END PROCESS;
END comportamiento;

Sesión 7/Primer '1'/not2.vhd
ENTITY not2 IS
	GENERIC (retardo: TIME:= 1 ns);
	PORT (e: IN BIT; sal: OUT BIT);
END not2;

ARCHITECTURE comportamiento OF not2 IS
BEGIN
	PROCESS (e)
	BEGIN
		sal <= NOT e AFTER retardo;
	END PROCESS;
END comportamiento;

Sesión 3/Con limitaciones/sumador.vhd
ENTITY sumador IS
	PORT (x, y, c_in: IN BIT; s, c_out:OUT BIT);
END sumador;

ARCHITECTURE estructural OF sumador IS
	COMPONENT and2
		PORT (e1, e2: IN BIT; sal: OUT BIT);
	END COMPONENT;
	COMPONENT or2
		PORT (e1, e2: IN BIT; sal: OUT BIT);
	END COMPONENT;
	COMPONENT not2
		PORT (e: IN BIT; sal: OUT BIT);
	END COMPONENT;
	SIGNAL not_x, not_y, not_c_in, s_and1_1, s_and1_2, s_and2_1, s_and2_2, s_and3_1, s_and3_2, s_and4_1, s_and4_2, c_out_and1, c_out_and2, c_out_and3, cout_aux, s1, s2: BIT;
BEGIN
	notx: not2 PORT MAP (x, not_x);
	noty: not2 PORT MAP (y, not_y);
	notc_in: not2 PORT MAP (c_in, not_c_in);
	and1_sal_1: and2 PORT MAP (x, not_y, s_and1_1);
	and1_sal_2: and2 PORT MAP (s_and1_1, not_c_in, s_and1_2);
	and2_sal_1: and2 PORT MAP (not_x, y, s_and2_1);
	and2_sal_2: and2 PORT MAP (s_and2_1, not_c_in, s_and2_2);
	and3_sal_1: and2 PORT MAP (not_x, not_y, s_and3_1);
	and3_sal_2: and2 PORT MAP (s_and3_1, c_in, s_and3_2);
	and4_sal_1: and2 PORT MAP (x, y, s_and4_1);
	and4_sal_2: and2 PORT MAP (s_and4_1, c_in, s_and4_2);
	sal1: or2 PORT MAP (s_and1_2, s_and2_2, s1);
	sal2: or2 PORT MAP (s_and3_2, s_and4_2, s2);
	sal: or2 PORT MAP (s1, s2, s);
	and1_c_out: and2 PORT MAP (x, y, c_out_and1);
	and2_c_out: and2 PORT MAP (x, c_in, c_out_and2);
	and3_c_out: and2 PORT MAP (y, c_in, c_out_and3);
	aux_cout: or2 PORT MAP (c_out_and1, c_out_and2, cout_aux);
	cout: or2 PORT MAP (cout_aux, c_out_and3, c_out);
END estructural;

Sesión 3/Sin limitaciones/tb_sumador.vhd
ENTITY tb_sumador IS
END tb_sumador;

ARCHITECTURE estructural OF tb_sumador IS

	COMPONENT sumador
		PORT (x, y, c_in: IN BIT; s, c_out: OUT BIT);
	END COMPONENT;
	

	FOR componente: sumador USE ENTITY WORK.sumador(estructural);


	SIGNAL a, b, c0, marca: BIT:='0';
	SIGNAL r, c1: BIT:='0';


BEGIN

	componente: sumador PORT MAP (a, b, c0, r, c1);
	
	
	PROCESS
	BEGIN
		a<= '1';
		b<= '1';
		c0<= '1';
		marca<= '1';
		WAIT UNTIL r<= '1' and c1<= '1';
		marca<= '0';
		WAIT FOR 5 ns;
		
		a<= '1';
		b<= '1';
		c0<= '0';
		marca<= '1';
		WAIT UNTIL r<= '0' and c1<= '1';
		marca<= '0';
		WAIT FOR 5 ns;
		
		a<= '1';
		b<= '0';
		c0<= '0';
		marca<= '1';
		WAIT UNTIL r<= '1' and c1<= '0';
		marca<= '0';
		WAIT FOR 5 ns;
		
		a<= '1';
		b<= '0';
		c0<= '1';
		marca<= '1';
		WAIT UNTIL r<= '0' and c1<= '1';
		marca<= '0';
		WAIT FOR 5 ns;
		
		a<= '0';
		b<= '1';
		c0<= '0';
		marca<= '1';
		WAIT UNTIL r<= '1' and c1<= '0';
		marca<= '0';
		WAIT FOR 5 ns;
		
		a<= '0';
		b<= '1';
		c0<= '1';
		marca<= '1';
		WAIT UNTIL r<= '0' and c1<= '1';
		marca<= '0';
		WAIT FOR 5 ns;
		
		a<= '0';
		b<= '0';
		c0<= '1';
		marca<= '1';
		WAIT UNTIL r<= '1' and c1<= '0';
		marca<= '0';
		WAIT FOR 5 ns;
		
		a<= '0';
		b<= '0';
		c0<= '0';
		marca<= '1';
		WAIT UNTIL r<= '0' and c1<= '0';
		marca<= '0';
		WAIT FOR 5 ns;
		
		WAIT;
	END PROCESS;
END estructural;

Sesión 3/Con limitaciones/cronograma.vcd
$date
  Sun Nov  8 11:34:06 2020
$end
$version
  GHDL v0
$end
$timescale
  1 fs
$end
$scope module standard $end
$upscope $end
$scope module tb_sumador $end
$var reg 1 ! a $end
$var reg 1 " b $end
$var reg 1 # c0 $end
$var reg 1 $ marca $end
$var reg 1 % r $end
$var reg 1 & c1 $end
$scope module componente $end
$var reg 1 ' x $end
$var reg 1 ( y $end
$var reg 1 ) c_in $end
$var reg 1 * s $end
$var reg 1 + c_out $end
$var reg 1 , not_x $end
$var reg 1 - not_y $end
$var reg 1 . not_c_in $end
$var reg 1 / s_and1_1 $end
$var reg 1 0 s_and1_2 $end
$var reg 1 1 s_and2_1 $end
$var reg 1 2 s_and2_2 $end
$var reg 1 3 s_and3_1 $end
$var reg 1 4 s_and3_2 $end
$var reg 1 5 s_and4_1 $end
$var reg 1 6 s_and4_2 $end
$var reg 1 7 c_out_and1 $end
$var reg 1 8 c_out_and2 $end
$var reg 1 9 c_out_and3 $end
$var reg 1 : cout_aux $end
$var reg 1 ; s1 $end
$var reg 1 < s2 $end
$scope module notx $end
$var reg 1 = e $end
$var reg 1 > sal $end
$upscope $end
$scope module noty $end
$var reg 1 ? e $end
$var reg 1 @ sal $end
$upscope $end
$scope module notc_in $end
$var reg 1 A e $end
$var reg 1 B sal $end
$upscope $end
$scope module and1_sal_1 $end
$var reg 1 C e1 $end
$var reg 1 D e2 $end
$var reg 1 E sal $end
$upscope $end
$scope module and1_sal_2 $end
$var reg 1 F e1 $end
$var reg 1 G e2 $end
$var reg 1 H sal $end
$upscope $end
$scope module and2_sal_1 $end
$var reg 1 I e1 $end
$var reg 1 J e2 $end
$var reg 1 K sal $end
$upscope $end
$scope module and2_sal_2 $end
$var reg 1 L e1 $end
$var reg 1 M e2 $end
$var reg 1 N sal $end
$upscope $end
$scope module and3_sal_1 $end
$var reg 1 O e1 $end
$var reg 1 P e2 $end
$var reg 1 Q sal $end
$upscope $end
$scope module and3_sal_2 $end
$var reg 1 R e1 $end
$var reg 1 S e2 $end
$var reg 1 T sal $end
$upscope $end
$scope module and4_sal_1 $end
$var reg 1 U e1 $end
$var reg 1 V e2 $end
$var reg 1 W sal $end
$upscope $end
$scope module and4_sal_2 $end
$var reg 1 X e1 $end
$var reg 1 Y e2 $end
$var reg 1 Z sal $end
$upscope $end
$scope module sal1 $end
$var reg 1 [ e1 $end
$var reg 1 \ e2 $end
$var reg 1 ] sal $end
$upscope $end
$scope module sal2 $end
$var reg 1 ^ e1 $end
$var reg 1 _ e2 $end
$var reg 1 ` sal $end
$upscope $end
$scope module sal $end
$var reg 1 a e1 $end
$var reg 1 b e2 $end
$var reg 1 c sal $end
$upscope $end
$scope module and1_c_out $end
$var reg 1 d e1 $end
$var reg 1 e e2 $end
$var reg 1 f sal $end
$upscope $end
$scope module and2_c_out $end
$var reg 1 g e1 $end
$var reg 1 h e2 $end
$var reg 1 i sal $end
$upscope $end
$scope module and3_c_out $end
$var reg 1 j e1 $end
$var reg 1 k e2 $end
$var reg 1 l sal $end
$upscope $end
$scope module aux_cout $end
$var reg 1 m e1 $end
$var reg 1 n e2 $end
$var reg 1 o sal $end
$upscope $end
$scope module cout $end
$var reg 1 p e1 $end
$var reg 1 q e2 $end
$var reg 1 r sal $end
$upscope $end
$upscope $end
$upscope $end
$enddefinitions $end
#0
1!
1"
0#
1$
0%
0&
1'
1(
0)
0*
0+
0,
0-
0.
0/
00
01
02
03
04
05
06
07
08
09
0:
0;
0<
1=
0>
1?
0@
0A
0B
1C
0D
0E
0F
0G
0H
0I
1J
0K
0L
0M
0N
0O
0P
0Q
0R
0S
0T
1U
1V
0W
0X
0Y
0Z
0[
0\
0]
0^
0_
0`
0a
0b
0c
1d
1e
0f
1g
0h
0i
1j
0k
0l
0m
0n
0o
0p
0q
0r
#1000000
1.
0>
0@
1B
1G
1M
#2000000
0*
0+
15
17
0E
0H
0K
0N
0Q
0T
1W
1X
0Z
0]
0`
0c
1f
0i
0l
1m
0o
0r
#3000000
0H
0N
#4000000
1:
0Z
1o
1p
#6000000
0$
1&
1+
1r
#11000000
0"
1$
0(
0?
0J
0V
0e
0j
#12000000
1-
1@
1D
1P
#13000000
05
07
0K
0W
0X
0f
0l
0m
#14000000
1/
1E
1F
0Q
#15000000
0:
0Z
0o
0p
#16000000
10
1H
1[
#17000000
0$
0&
0+
0r
#18000000
1;
1]
1a
#20000000
1%
1*
1c
#22000000
1"
1#
1$
1(
1)
1?
1A
1J
1S
1V
1Y
1e
1h
1j
1k
#23000000
0-
0.
0@
0B
0D
0G
0M
0P
#24000000
15
17
18
19
0K
0T
1W
1X
0Z
1f
1i
1l
1m
1n
1q
#25000000
0/
00
0E
0F
0H
0N
0Q
0[
#26000000
0$
1&
1+
16
1:
1Z
1_
1o
1p
1r
#27000000
0;
0H
0]
0a
#28000000
1+
1<
1`
1b
1r
#30000000
1*
1c
#31000000
0"
1$
0(
0?
0J
0V
0e
0j
#32000000
1-
1@
1D
1P
#33000000
05
07
09
0K
0W
0X
0f
0l
0m
0q
#34000000
1/
1E
1F
0Q
#35000000
1+
06
0Z
0_
1o
1r
#36000000
0H
#37000000
0<
0`
0b
#39000000
0$
0%
0*
0c
#44000000
0!
1"
0#
1$
0'
1(
0)
0=
1?
0A
0C
1J
0S
0U
1V
0Y
0d
1e
0g
0h
1j
0k
#45000000
1,
0-
1.
1>
0@
1B
0D
1G
1I
1M
1O
0P
#46000000
0/
08
0E
0F
0T
0W
0Z
0f
0i
0l
0n
#47000000
11
0E
1K
1L
0N
0Q
#48000000
0:
0H
0o
0p
#49000000
12
1N
1\
#50000000
0$
0&
0+
0r
#51000000
1;
1]
1a
#53000000
1%
1*
1c
#55000000
1#
1$
1)
1A
1S
1Y
1h
1k
#56000000
0.
0B
0G
0M
#57000000
19
0T
0Z
0i
1l
1q
#58000000
02
0H
0N
0\
#59000000
1&
1+
1r
#60000000
0;
0]
0a
#62000000
0$
0%
0*
0c
#67000000
0"
1$
0(
0?
0J
0V
0e
0j
#68000000
1-
1@
1D
1P
#69000000
01
09
0K
0L
0W
0f
0l
0q
#70000000
13
0E
1Q
1R
#71000000
0$
0&
0+
0N
0r
#72000000
14
1T
1^
#74000000
1<
1`
1b
#76000000
0#
1$
1%
0)
1*
0A
0S
0Y
1c
0h
0k
#77000000
1.
1B
1G
1M
#78000000
04
0T
0Z
0^
0i
0l
#79000000
0H
0N
#80000000
0<
0`
0b
#82000000
0$
0%
0*
0c
