Sesión 3/Sin limitaciones/or4.vhd
ENTITY or4 IS
	GENERIC (retardo: TIME:= 2 ns);
	PORT (e1, e2, e3, e4: IN BIT; sal: OUT BIT);
END or4;

ARCHITECTURE comportamiento OF or4 IS
BEGIN
	PROCESS (e1, e2, e3, e4)
	BEGIN
		sal <= e1 OR e2 OR e3 OR e4 AFTER retardo;
	END PROCESS;
END comportamiento;

Sesión 3/Sin limitaciones/and3.vhd
ENTITY and3 IS
	GENERIC (retardo: TIME:= 2 ns);
	PORT (e1, e2, e3: IN BIT; sal: OUT BIT);
END and3;

ARCHITECTURE comportamiento OF and3 IS
BEGIN
	PROCESS (e1, e2, e3)
	BEGIN
		sal <= e1 AND e2 AND e3 AFTER retardo;
	END PROCESS;
END comportamiento;

Sesión 7/Primer '1'/not2.vhd
ENTITY not2 IS
	GENERIC (retardo: TIME:= 1 ns);
	PORT (e: IN BIT; sal: OUT BIT);
END not2;

ARCHITECTURE comportamiento OF not2 IS
BEGIN
	PROCESS (e)
	BEGIN
		sal <= NOT e AFTER retardo;
	END PROCESS;
END comportamiento;

Sesión 3/Sin limitaciones/sumador.vhd
ENTITY sumador IS
	PORT (x, y, c_in: IN BIT; s, c_out:OUT BIT);
END sumador;

ARCHITECTURE estructural OF sumador IS
	COMPONENT and3
		PORT (e1, e2, e3: IN BIT; sal: OUT BIT);
	END COMPONENT;
	COMPONENT or4
		PORT (e1, e2, e3, e4: IN BIT; sal: OUT BIT);
	END COMPONENT;
	COMPONENT not2
		PORT (e: IN BIT; sal: OUT BIT);
	END COMPONENT;
	SIGNAL not_x, not_y, not_c_in, s_and1, s_and2, s_and3, s_and4, c_out_and1, c_out_and2, c_out_and3: BIT;
BEGIN
	notx: not2 PORT MAP (x, not_x);
	noty: not2 PORT MAP (y, not_y);
	notc_in: not2 PORT MAP (c_in, not_c_in);
	and1_sal: and3 PORT MAP (x, not_y, not_c_in, s_and1);
	and2_sal: and3 PORT MAP (not_x, y, not_c_in, s_and2);
	and3_sal: and3 PORT MAP (not_x, not_y, c_in, s_and3);
	and4_sal: and3 PORT MAP (x, y, c_in, s_and4);
	sal: or4 PORT MAP (s_and1, s_and2, s_and3, s_and4, s);
	and1_c_out: and3 PORT MAP (x, y, '1', c_out_and1);
	and2_c_out: and3 PORT MAP (x, c_in, '1', c_out_and2);
	and3_c_out: and3 PORT MAP (y, c_in, '1', c_out_and3);
	cout: or4 PORT MAP (c_out_and1, c_out_and2, c_out_and3, '0', c_out);
END estructural;

Sesión 3/Sin limitaciones/tb_sumador.vhd
ENTITY tb_sumador IS
END tb_sumador;

ARCHITECTURE estructural OF tb_sumador IS

	COMPONENT sumador
		PORT (x, y, c_in: IN BIT; s, c_out: OUT BIT);
	END COMPONENT;
	

	FOR componente: sumador USE ENTITY WORK.sumador(estructural);


	SIGNAL a, b, c0, marca: BIT:='0';
	SIGNAL r, c1: BIT:='0';


BEGIN

	componente: sumador PORT MAP (a, b, c0, r, c1);
	
	
	PROCESS
	BEGIN
		a<= '1';
		b<= '1';
		c0<= '1';
		marca<= '1';
		WAIT UNTIL r<= '1' and c1<= '1';
		marca<= '0';
		WAIT FOR 5 ns;
		
		a<= '1';
		b<= '1';
		c0<= '0';
		marca<= '1';
		WAIT UNTIL r<= '0' and c1<= '1';
		marca<= '0';
		WAIT FOR 5 ns;
		
		a<= '1';
		b<= '0';
		c0<= '0';
		marca<= '1';
		WAIT UNTIL r<= '1' and c1<= '0';
		marca<= '0';
		WAIT FOR 5 ns;
		
		a<= '1';
		b<= '0';
		c0<= '1';
		marca<= '1';
		WAIT UNTIL r<= '0' and c1<= '1';
		marca<= '0';
		WAIT FOR 5 ns;
		
		a<= '0';
		b<= '1';
		c0<= '0';
		marca<= '1';
		WAIT UNTIL r<= '1' and c1<= '0';
		marca<= '0';
		WAIT FOR 5 ns;
		
		a<= '0';
		b<= '1';
		c0<= '1';
		marca<= '1';
		WAIT UNTIL r<= '0' and c1<= '1';
		marca<= '0';
		WAIT FOR 5 ns;
		
		a<= '0';
		b<= '0';
		c0<= '1';
		marca<= '1';
		WAIT UNTIL r<= '1' and c1<= '0';
		marca<= '0';
		WAIT FOR 5 ns;
		
		a<= '0';
		b<= '0';
		c0<= '0';
		marca<= '1';
		WAIT UNTIL r<= '0' and c1<= '0';
		marca<= '0';
		WAIT FOR 5 ns;
		
		WAIT;
	END PROCESS;
END estructural;

Sesión 3/Sin limitaciones/cronograma.vcd
$date
  Tue Nov  3 23:12:44 2020
$end
$version
  GHDL v0
$end
$timescale
  1 fs
$end
$scope module standard $end
$upscope $end
$scope module tb_sumador $end
$var reg 1 ! a $end
$var reg 1 " b $end
$var reg 1 # c0 $end
$var reg 1 $ marca $end
$var reg 1 % r $end
$var reg 1 & c1 $end
$scope module componente $end
$var reg 1 ' x $end
$var reg 1 ( y $end
$var reg 1 ) c_in $end
$var reg 1 * s $end
$var reg 1 + c_out $end
$var reg 1 , not_x $end
$var reg 1 - not_y $end
$var reg 1 . not_c_in $end
$var reg 1 / s_and1 $end
$var reg 1 0 s_and2 $end
$var reg 1 1 s_and3 $end
$var reg 1 2 s_and4 $end
$var reg 1 3 c_out_and1 $end
$var reg 1 4 c_out_and2 $end
$var reg 1 5 c_out_and3 $end
$scope module notx $end
$var reg 1 6 e $end
$var reg 1 7 sal $end
$upscope $end
$scope module noty $end
$var reg 1 8 e $end
$var reg 1 9 sal $end
$upscope $end
$scope module notc_in $end
$var reg 1 : e $end
$var reg 1 ; sal $end
$upscope $end
$scope module and1_sal $end
$var reg 1 < e1 $end
$var reg 1 = e2 $end
$var reg 1 > e3 $end
$var reg 1 ? sal $end
$upscope $end
$scope module and2_sal $end
$var reg 1 @ e1 $end
$var reg 1 A e2 $end
$var reg 1 B e3 $end
$var reg 1 C sal $end
$upscope $end
$scope module and3_sal $end
$var reg 1 D e1 $end
$var reg 1 E e2 $end
$var reg 1 F e3 $end
$var reg 1 G sal $end
$upscope $end
$scope module and4_sal $end
$var reg 1 H e1 $end
$var reg 1 I e2 $end
$var reg 1 J e3 $end
$var reg 1 K sal $end
$upscope $end
$scope module sal $end
$var reg 1 L e1 $end
$var reg 1 M e2 $end
$var reg 1 N e3 $end
$var reg 1 O e4 $end
$var reg 1 P sal $end
$upscope $end
$scope module and1_c_out $end
$var reg 1 Q e1 $end
$var reg 1 R e2 $end
$var reg 1 S e3 $end
$var reg 1 T sal $end
$upscope $end
$scope module and2_c_out $end
$var reg 1 U e1 $end
$var reg 1 V e2 $end
$var reg 1 W e3 $end
$var reg 1 X sal $end
$upscope $end
$scope module and3_c_out $end
$var reg 1 Y e1 $end
$var reg 1 Z e2 $end
$var reg 1 [ e3 $end
$var reg 1 \ sal $end
$upscope $end
$scope module cout $end
$var reg 1 ] e1 $end
$var reg 1 ^ e2 $end
$var reg 1 _ e3 $end
$var reg 1 ` e4 $end
$var reg 1 a sal $end
$upscope $end
$upscope $end
$upscope $end
$enddefinitions $end
#0
1!
1"
1#
1$
0%
0&
1'
1(
1)
0*
0+
0,
0-
0.
0/
00
01
02
03
04
05
16
07
18
09
1:
0;
1<
0=
0>
0?
0@
1A
0B
0C
0D
0E
1F
0G
1H
1I
1J
0K
0L
0M
0N
0O
0P
1Q
1R
1S
0T
1U
1V
1W
0X
1Y
1Z
1[
0\
0]
0^
0_
0`
0a
#1000000
07
09
0;
#2000000
0*
0+
12
13
14
15
0?
0C
0G
1K
1O
0P
1T
1X
1\
1]
1^
1_
0a
#4000000
0$
1%
1&
1*
1+
1P
1a
#9000000
0#
1$
0)
0:
0F
0J
0V
0Z
#10000000
1.
1;
1>
1B
#11000000
02
04
05
0G
0K
0O
0X
0\
0^
0_
#12000000
0?
0C
#13000000
0$
0%
0*
1+
0P
1a
#18000000
0"
1$
0(
08
0A
0I
0R
0Y
#19000000
1-
19
1=
1E
#20000000
03
0C
0K
0T
0\
0]
#21000000
1/
1?
0G
1L
#22000000
0$
0&
0+
0a
#23000000
1%
1*
1P
#27000000
1#
1$
1)
1:
1F
1J
1V
1Z
#28000000
0.
0;
0>
0B
#29000000
14
0G
0K
1X
0\
1^
#30000000
0/
0?
0C
0L
#31000000
1&
1+
1a
#32000000
0$
0%
0*
0P
#37000000
0!
1"
0#
1$
0'
1(
0)
06
18
0:
0<
1A
0F
0H
1I
0J
0Q
1R
0U
0V
1Y
0Z
#38000000
1,
0-
1.
17
09
1;
0=
1>
1@
1B
1D
0E
#39000000
04
0?
0G
0K
0T
0X
0\
0^
#40000000
10
0?
1C
0G
1M
#41000000
0$
0&
0+
0a
#42000000
1%
1*
1P
#46000000
1#
1$
1)
1:
1F
1J
1V
1Z
#47000000
0.
0;
0>
0B
#48000000
15
0G
0K
0X
1\
1_
#49000000
00
0?
0C
0M
#50000000
1&
1+
1a
#51000000
0$
0%
0*
0P
#56000000
0"
1$
0(
08
0A
0I
0R
0Y
#57000000
1-
19
1=
1E
#58000000
05
0C
0K
0T
0\
0_
#59000000
11
0?
1G
1N
#60000000
0$
0&
0+
0a
#61000000
1%
1*
1P
#65000000
0#
1$
0)
0:
0F
0J
0V
0Z
#66000000
1.
1;
1>
1B
#67000000
01
0G
0K
0N
0X
0\
#68000000
0?
0C
#69000000
0$
0%
0*
0P
