Sesión 2/XOR/xor2.vhd
--puerta and de 2 entradas

ENTITY xor2 IS
	GENERIC (retardo: TIME:= 2 ns);
	PORT (e1, e2: IN BIT; sal: OUT BIT);
END xor2;

ARCHITECTURE comportamiento OF xor2 IS
BEGIN
	PROCESS (e1, e2)
	BEGIN
		sal <= e1 XOR e2 AFTER retardo;
	END PROCESS;
END comportamiento;

Sesión 0/XOR/tb_xor2.vhd
ENTITY tb_xor2 IS
END tb_xor2;

ARCHITECTURE estructural OF tb_xor2 IS

	COMPONENT xor2
		PORT (e1, e2: IN BIT; sal: OUT BIT);
	END COMPONENT;
	

	FOR componente: xor2 USE ENTITY WORK.xor2(comportamiento);


	SIGNAL a, b: BIT:='0';
	SIGNAL s: BIT:='0';


BEGIN

	componente: xor2 PORT MAP (a, b, s);
	
	
	PROCESS
	BEGIN
		a<= '0';
		b<= '0';
		WAIT FOR 5 ns;
		a<= '1';
		b<= '0';
		WAIT FOR 5 ns;
		a<= '0';
		b<= '1';
		WAIT FOR 5 ns;
		a<= '1';
		b<= '1';
		WAIT FOR 5 ns;
		WAIT;
	END PROCESS;
END estructural;

Sesión 0/XOR/cronograma.vcd
$date
  Tue Oct 13 14:01:41 2020
$end
$version
  GHDL v0
$end
$timescale
  1 fs
$end
$scope module standard $end
$upscope $end
$scope module tb_xor2 $end
$var reg 1 ! a $end
$var reg 1 " b $end
$var reg 1 # s $end
$scope module componente $end
$var reg 1 $ e1 $end
$var reg 1 % e2 $end
$var reg 1 & sal $end
$upscope $end
$upscope $end
$enddefinitions $end
#0
0!
0"
0#
0$
0%
0&
#3000000
0&
#5000000
1!
1$
#8000000
1#
1&
#10000000
0!
1"
0$
1%
#13000000
1&
#15000000
1!
1$
#18000000
0#
0&
