Sesión 7/Primer '1'/not2.vhd
ENTITY not2 IS
	GENERIC (retardo: TIME:= 1 ns);
	PORT (e: IN BIT; sal: OUT BIT);
END not2;

ARCHITECTURE comportamiento OF not2 IS
BEGIN
	PROCESS (e)
	BEGIN
		sal <= NOT e AFTER retardo;
	END PROCESS;
END comportamiento;

Sesión 1/NOT/op_not_4.vhd
ENTITY op_not_4 IS
	PORT (vector_a: IN BIT_VECTOR (3 DOWNTO 0);
				vector_r: OUT BIT_VECTOR (3 DOWNTO 0));
END op_not_4;

ARCHITECTURE estructural OF op_not_4 IS
	COMPONENT not2
		PORT (e: IN BIT; sal: OUT BIT);
	END COMPONENT;
	FOR ALL: not2 USE ENTITY WORK.not2(comportamiento);
BEGIN
	celda0: not2 PORT MAP (vector_a(0), vector_r(0));
	celda1: not2 PORT MAP (vector_a(1), vector_r(1));
	celda2: not2 PORT MAP (vector_a(2), vector_r(2));
	celda3: not2 PORT MAP (vector_a(3), vector_r(3));
END estructural;

Sesión 1/NOT/tb_op_not_4.vhd
--este es el test_bench de un operador AND de 4 bits
ENTITY tb_op_not_4 IS
END tb_op_not_4;

ARCHITECTURE estructural OF tb_op_not_4 IS
--declaración del componente a estudiar
	COMPONENT op_not_4
			PORT (vector_a: IN BIT_VECTOR (3 DOWNTO 0);
						vector_r: OUT BIT_VECTOR (3 DOWNTO 0));
	END COMPONENT;
--especificación de la configuración del componente
	FOR componente: op_not_4 USE ENTITY WORK.op_not_4(estructural);
--declaración de señales de interconexión
	SIGNAL A, B: BIT_VECTOR (3 DOWNTO 0):= X"0";
--comienza la descripción de los procesos
BEGIN
--primer proceso: instalación del componente a estudiar
	componente: op_not_4 PORT MAP (A, B);
--segudno proceso: estímulo de las señales de entrada
	PROCESS
		TYPE tipo_patron IS RECORD
--entradas a la puerta
			a, b: BIT_VECTOR (3 DOWNTO 0);
		END RECORD;
--la tabla de verdad
		TYPE array_patron IS ARRAY (NATURAL RANGE <>) of tipo_patron;
		CONSTANT tabla_verdad: array_patron :=
		((X"0", X"F"),
		(X"A", X"5"),
		(X"F", X"0"),
		(X"3", X"C"));
	BEGIN
--inyecta las señales desde la tabla de verdad
		FOR i IN tabla_verdad'RANGE LOOP
			A <= tabla_verdad(i).a;
--espero al resultado
			WAIT FOR 5 ns;
--compruebo si es correcto
			ASSERT B = tabla_verdad(i).b REPORT "resultado incorrecto" SEVERITY ERROR;
		END LOOP;
--mensaje final
		ASSERT false REPORT "fin del test" SEVERITY NOTE;
		WAIT;
	END PROCESS;
END estructural;

Sesión 1/NOT/cronograma.vcd
$date
  Sat Oct 24 14:14:07 2020
$end
$version
  GHDL v0
$end
$timescale
  1 fs
$end
$scope module standard $end
$upscope $end
$scope module tb_op_not_4 $end
$var reg 4 ! a[3:0] $end
$var reg 4 " b[3:0] $end
$scope module componente $end
$var reg 4 # vector_a[3:0] $end
$var reg 4 $ vector_r[3:0] $end
$scope module celda0 $end
$var reg 1 % e $end
$var reg 1 & sal $end
$upscope $end
$scope module celda1 $end
$var reg 1 ' e $end
$var reg 1 ( sal $end
$upscope $end
$scope module celda2 $end
$var reg 1 ) e $end
$var reg 1 * sal $end
$upscope $end
$scope module celda3 $end
$var reg 1 + e $end
$var reg 1 , sal $end
$upscope $end
$upscope $end
$upscope $end
$enddefinitions $end
#0
b0000 !
b0000 "
b0000 #
b0000 $
0%
0&
0'
0(
0)
0*
0+
0,
#1000000
b1111 "
b1111 $
1&
1(
1*
1,
#5000000
b1010 !
b1010 #
1'
1+
#6000000
b0101 "
b0101 $
0(
0,
#10000000
b1111 !
b1111 #
1%
1)
#11000000
b0000 "
b0000 $
0&
0*
#15000000
b0011 !
b0011 #
0)
0+
#16000000
b1100 "
b1100 $
1*
1,
