Sesión 2/XOR/xor2.vhd
--puerta and de 2 entradas

ENTITY xor2 IS
	GENERIC (retardo: TIME:= 2 ns);
	PORT (e1, e2: IN BIT; sal: OUT BIT);
END xor2;

ARCHITECTURE comportamiento OF xor2 IS
BEGIN
	PROCESS (e1, e2)
	BEGIN
		sal <= e1 XOR e2 AFTER retardo;
	END PROCESS;
END comportamiento;

Sesión 1/XOR/op_xor_4.vhd
ENTITY op_xor_4 IS
	PORT (vector_a, vector_b: IN BIT_VECTOR (3 DOWNTO 0);
				vector_r: OUT BIT_VECTOR (3 DOWNTO 0));
END op_xor_4;

ARCHITECTURE estructural OF op_xor_4 IS
	COMPONENT xor2
		PORT (e1, e2: IN BIT; sal: OUT BIT);
	END COMPONENT;
	FOR ALL: xor2 USE ENTITY WORK.xor2(comportamiento);
BEGIN
	celda0: xor2 PORT MAP (vector_a(0), vector_b(0), vector_r(0));
	celda1: xor2 PORT MAP (vector_a(1), vector_b(1), vector_r(1));
	celda2: xor2 PORT MAP (vector_a(2), vector_b(2), vector_r(2));
	celda3: xor2 PORT MAP (vector_a(3), vector_b(3), vector_r(3));
END estructural;

Sesión 1/XOR/tb_op_xor_4.vhd
--este es el test_bench de un operador AND de 4 bits
ENTITY tb_op_xor_4 IS
END tb_op_xor_4;

ARCHITECTURE estructural OF tb_op_xor_4 IS
--declaración del componente a estudiar
	COMPONENT op_xor_4
			PORT (vector_a, vector_b: IN BIT_VECTOR (3 DOWNTO 0);
						vector_r: OUT BIT_VECTOR (3 DOWNTO 0));
	END COMPONENT;
--especificación de la configuración del componente
	FOR componente: op_xor_4 USE ENTITY WORK.op_xor_4(estructural);
--declaración de señales de interconexión
	SIGNAL A, B, C: BIT_VECTOR (3 DOWNTO 0):= X"0";
--comienza la descripción de los procesos
BEGIN
--primer proceso: instalación del componente a estudiar
	componente: op_xor_4 PORT MAP (A, B, C);
--segudno proceso: estímulo de las señales de entrada
	PROCESS
		TYPE tipo_patron IS RECORD
--entradas a la puerta
			a, b, c: BIT_VECTOR (3 DOWNTO 0);
		END RECORD;
--la tabla de verdad
		TYPE array_patron IS ARRAY (NATURAL RANGE <>) of tipo_patron;
		CONSTANT tabla_verdad: array_patron :=
		((X"0", X"0", X"0"),
		(X"A", X"F", X"5"),
		(X"F", X"7", X"8"),
		(X"3", X"A", X"9"));
	BEGIN
--inyecta las señales desde la tabla de verdad
		FOR i IN tabla_verdad'RANGE LOOP
			A <= tabla_verdad(i).a;
			B <= tabla_verdad(i).b;
--espero al resultado
			WAIT FOR 5 ns;
--compruebo si es correcto
			ASSERT C = tabla_verdad(i).c REPORT "resultado incorrecto" SEVERITY ERROR;
		END LOOP;
--mensaje final
		ASSERT false REPORT "fin del test" SEVERITY NOTE;
		WAIT;
	END PROCESS;
END estructural;

Sesión 1/XOR/cronograma.vcd
$date
  Sun Oct 18 00:24:22 2020
$end
$version
  GHDL v0
$end
$timescale
  1 fs
$end
$scope module standard $end
$upscope $end
$scope module tb_op_xor_4 $end
$var reg 4 ! a[3:0] $end
$var reg 4 " b[3:0] $end
$var reg 4 # c[3:0] $end
$scope module componente $end
$var reg 4 $ vector_a[3:0] $end
$var reg 4 % vector_b[3:0] $end
$var reg 4 & vector_r[3:0] $end
$scope module celda0 $end
$var reg 1 ' e1 $end
$var reg 1 ( e2 $end
$var reg 1 ) sal $end
$upscope $end
$scope module celda1 $end
$var reg 1 * e1 $end
$var reg 1 + e2 $end
$var reg 1 , sal $end
$upscope $end
$scope module celda2 $end
$var reg 1 - e1 $end
$var reg 1 . e2 $end
$var reg 1 / sal $end
$upscope $end
$scope module celda3 $end
$var reg 1 0 e1 $end
$var reg 1 1 e2 $end
$var reg 1 2 sal $end
$upscope $end
$upscope $end
$upscope $end
$enddefinitions $end
#0
b0000 !
b0000 "
b0000 #
b0000 $
b0000 %
b0000 &
0'
0(
0)
0*
0+
0,
0-
0.
0/
00
01
02
#3000000
b0000 &
0)
0,
0/
02
#5000000
b1010 !
b1111 "
b1010 $
b1111 %
1(
1*
1+
1.
10
11
#8000000
b0101 #
b0101 &
1)
0,
1/
02
#10000000
b1111 !
b0111 "
b1111 $
b0111 %
1'
1-
01
#13000000
b1000 #
b1000 &
0)
0/
12
#15000000
b0011 !
b1010 "
b0011 $
b1010 %
0(
0-
0.
00
11
#18000000
b1001 #
b1001 &
1)
0/
12
