Sesión 0/OR/or2.vhd
ENTITY or2 IS
	GENERIC (retardo: TIME:= 2 ns);
	PORT (e1, e2: IN BIT; sal: OUT BIT);
END or2;

ARCHITECTURE comportamiento OF or2 IS
BEGIN
	PROCESS (e1, e2)
	BEGIN
		sal <= e1 OR e2 AFTER retardo;
	END PROCESS;
END comportamiento;

Sesión 0/OR/tb_or2.vhd
ENTITY tb_or2 IS
END tb_or2;

ARCHITECTURE estructural OF tb_or2 IS

	COMPONENT or2
		PORT (e1, e2: IN BIT; sal: OUT BIT);
	END COMPONENT;
	

	FOR componente: or2 USE ENTITY WORK.or2(comportamiento);


	SIGNAL a, b: BIT:='0';
	SIGNAL s: BIT:='0';


BEGIN

	componente: or2 PORT MAP (a, b, s);
	
	
	PROCESS
	BEGIN
		a<= '0';
		b<= '0';
		WAIT FOR 5 ns;
		a<= '1';
		b<= '0';
		WAIT FOR 5 ns;
		a<= '0';
		b<= '1';
		WAIT FOR 5 ns;
		a<= '1';
		b<= '1';
		WAIT FOR 5 ns;
		WAIT;
	END PROCESS;
END estructural;

Sesión 0/OR/cronograma.vcd
$date
  Tue Oct 13 14:05:53 2020
$end
$version
  GHDL v0
$end
$timescale
  1 fs
$end
$scope module standard $end
$upscope $end
$scope module tb_or2 $end
$var reg 1 ! a $end
$var reg 1 " b $end
$var reg 1 # s $end
$scope module componente $end
$var reg 1 $ e1 $end
$var reg 1 % e2 $end
$var reg 1 & sal $end
$upscope $end
$upscope $end
$enddefinitions $end
#0
0!
0"
0#
0$
0%
0&
#2000000
0&
#5000000
1!
1$
#7000000
1#
1&
#10000000
0!
1"
0$
1%
#12000000
1&
#15000000
1!
1$
#17000000
1&
