Sesión 2/NOR/nor2.vhd
--puerta and de 2 entradas

ENTITY nor2 IS
	GENERIC (retardo: TIME:= 2 ns);
	PORT (e1, e2: IN BIT; sal: OUT BIT);
END nor2;

ARCHITECTURE comportamiento OF nor2 IS
BEGIN
	PROCESS (e1, e2)
	BEGIN
		sal <= e1 NOR e2 AFTER retardo;
	END PROCESS;
END comportamiento;

Sesión 2/NOR/op_nor_n.vhd
ENTITY op_nor_n IS
	GENERIC (n: INTEGER:=8);
	PORT (x, y: IN BIT_VECTOR(n-1 DOWNTO 0); r:OUT BIT_VECTOR(n-1 DOWNTO 0));
END op_nor_n;

ARCHITECTURE estructural OF op_nor_n IS
	COMPONENT nor2
		PORT (e1, e2: IN BIT; sal: OUT BIT);
	END COMPONENT;
BEGIN
	bateria: FOR i IN 0 TO n-1 GENERATE
		puertas: nor2 PORT MAP (x(i), y(i), r(i));
	END GENERATE;
END estructural;

Sesión 2/NOR/tb_op_nor_n.vhd
ENTITY tb_op_nor_n IS
END tb_op_nor_n;

ARCHITECTURE estructural OF tb_op_nor_n IS
	COMPONENT op_nor_n
		GENERIC (n: INTEGER:=8);
		PORT (x, y: IN BIT_VECTOR(n-1 DOWNTO 0); r: OUT BIT_VECTOR(n-1 DOWNTO 0));
	END COMPONENT;
	
	FOR operador: op_nor_n USE ENTITY WORK.op_nor_n(estructural);
	
	CONSTANT TAMANO_PALABRA: integer := 2;
	
	SIGNAL A, B, C: BIT_VECTOR(TAMANO_PALABRA-1 DOWNTO 0);

BEGIN
	operador: op_nor_n GENERIC MAP (TAMANO_PALABRA) PORT MAP(A, B, C);
	
	PROCESS
	VARIABLE valor, limite: INTEGER;
	BEGIN
		limite:= 2**TAMANO_PALABRA-1;
		
		FOR i IN 0 TO limite LOOP
			valor:=i;
			
			FOR k IN A'REVERSE_RANGE LOOP
				A(k)<=BIT'VAL(valor REM 2);
				valor:=valor/2;
			END LOOP;
			
			FOR j IN 0 TO limite LOOP
				valor:=j;
				
				FOR k IN B'REVERSE_RANGE LOOP
					B(k)<=BIT'VAL(valor REM 2);
					valor:=valor/2;
				END LOOP;
				WAIT FOR 2 ns;
				
			END LOOP;
		END LOOP;
		
		WAIT FOR 2 ns;
		WAIT;
	END PROCESS;
END estructural;

Sesión 2/NOR/cronograma.vcd
$date
  Fri Oct 23 19:23:38 2020
$end
$version
  GHDL v0
$end
$timescale
  1 fs
$end
$scope module standard $end
$upscope $end
$scope module tb_op_nor_n $end
$var reg 2 ! a[1:0] $end
$var reg 2 " b[1:0] $end
$var reg 2 # c[1:0] $end
$scope module operador $end
$var reg 2 $ x[1:0] $end
$var reg 2 % y[1:0] $end
$var reg 2 & r[1:0] $end
$scope module bateria(0) $end
$scope module puertas $end
$var reg 1 ' e1 $end
$var reg 1 ( e2 $end
$var reg 1 ) sal $end
$upscope $end
$upscope $end
$scope module bateria(1) $end
$scope module puertas $end
$var reg 1 * e1 $end
$var reg 1 + e2 $end
$var reg 1 , sal $end
$upscope $end
$upscope $end
$upscope $end
$upscope $end
$enddefinitions $end
#0
b00 !
b00 "
b00 #
b00 $
b00 %
b00 &
0'
0(
0)
0*
0+
0,
#2000000
b01 "
b11 #
b01 %
b11 &
1(
1)
1,
#4000000
b10 "
b10 #
b10 %
b10 &
0(
0)
1+
#6000000
b11 "
b01 #
b11 %
b01 &
1(
1)
0,
#8000000
b01 !
b00 "
b00 #
b01 $
b00 %
b00 &
1'
0(
0)
0+
#10000000
b01 "
b10 #
b01 %
b10 &
1(
0)
1,
#12000000
b10 "
b10 %
b10 &
0(
0)
1+
#14000000
b11 "
b00 #
b11 %
b00 &
1(
0)
0,
#16000000
b10 !
b00 "
b10 $
b00 %
b00 &
0'
0(
0)
1*
0+
#18000000
b01 "
b01 #
b01 %
b01 &
1(
1)
0,
#20000000
b10 "
b00 #
b10 %
b00 &
0(
0)
1+
#22000000
b11 "
b01 #
b11 %
b01 &
1(
1)
0,
#24000000
b11 !
b00 "
b00 #
b11 $
b00 %
b00 &
1'
0(
0)
0+
#26000000
b01 "
b01 %
b00 &
1(
0)
0,
#28000000
b10 "
b10 %
b00 &
0(
0)
1+
#30000000
b11 "
b11 %
b00 &
1(
0)
0,
#32000000
b00 &
0)
