Sesión 8/or2.vhd
ENTITY or2 IS
	GENERIC (retardo: TIME:= 1 ns);
	PORT (e1, e2: IN BIT; sal: OUT BIT);
END or2;

ARCHITECTURE comportamiento OF or2 IS
BEGIN
	PROCESS (e1, e2)
	BEGIN
		sal <= e1 OR e2 AFTER retardo;
	END PROCESS;
END comportamiento;

Sesión 7/Primer '0'/and2.vhd
ENTITY and2 IS
	GENERIC (retardo: TIME:= 1 ns);
	PORT (e1, e2: IN BIT; sal: OUT BIT);
END and2;

ARCHITECTURE comportamiento OF and2 IS
BEGIN
	PROCESS (e1, e2)
	BEGIN
		sal <= e1 AND e2 AFTER retardo;
	END PROCESS;
END comportamiento;

Sesión 2/XOR/xor2.vhd
--puerta and de 2 entradas

ENTITY xor2 IS
	GENERIC (retardo: TIME:= 2 ns);
	PORT (e1, e2: IN BIT; sal: OUT BIT);
END xor2;

ARCHITECTURE comportamiento OF xor2 IS
BEGIN
	PROCESS (e1, e2)
	BEGIN
		sal <= e1 XOR e2 AFTER retardo;
	END PROCESS;
END comportamiento;

Sesión 6/Bloque_P.vhd
ENTITY Bloque_P IS
	GENERIC (c: INTEGER:=4);
	PORT(x_in, y_in: IN BIT_VECTOR(c-1 downto 0); P: OUT BIT);
END ENTITY;

ARCHITECTURE estructural OF Bloque_P IS

COMPONENT and2 IS
	GENERIC (retardo: TIME:= 1 ns);
	PORT (e1, e2: IN BIT; sal: OUT BIT);
END COMPONENT;

COMPONENT xor2 IS
	GENERIC (retardo: TIME:= 3 ns);
	PORT (e1, e2: IN BIT; sal: OUT BIT);
END COMPONENT;

SIGNAL xor_0, xor_1, xor_2, xor_3, and_1, and_2: BIT;

BEGIN

	bit_0: xor2 PORT MAP(x_in(0), y_in(0), xor_0);
	bit_1: xor2 PORT MAP(x_in(1), y_in(1), xor_1);
	bit_2: xor2 PORT MAP(x_in(2), y_in(2), xor_2);
	bit_3: xor2 PORT MAP(x_in(3), y_in(3), xor_3);
	primer_and: and2 PORT MAP(xor_0, xor_1, and_1);
	segundo_and: and2 PORT MAP(xor_2, xor_3, and_2);
	tercer_and: and2 PORT MAP(and_1, and_2, P);

END ARCHITECTURE;

Sesión 6/semisumador.vhd
ENTITY semisumador IS
	PORT (x, y: IN BIT; r_xor, r_and:OUT BIT);
END semisumador;

ARCHITECTURE estructural OF semisumador IS
	COMPONENT xor2
		PORT (e1, e2: IN BIT; sal:OUT BIT);
	END COMPONENT;
	COMPONENT and2
		PORT (e1, e2: IN BIT; sal:OUT BIT);
	END COMPONENT;
BEGIN
		xor_n: xor2 PORT MAP (x, y, r_xor);
		and_n: and2 PORT MAP (x, y, r_and);
END estructural;

Sesión 6/sumador.vhd
ENTITY sumador IS
	PORT (x, y, c_in: IN BIT; s, c_out:OUT BIT);
END sumador;

ARCHITECTURE estructural OF sumador IS
	COMPONENT semisumador
		PORT (x, y: IN BIT; r_xor, r_and:OUT BIT);
	END COMPONENT;
	COMPONENT or2
		PORT (e1, e2: IN BIT; sal:OUT BIT);
	END COMPONENT;
	SIGNAL r_xor, r_and_1, r_and_2: BIT;
BEGIN
	primer_semisumador: semisumador PORT MAP(x, y, r_xor, r_and_1);
	segundo_semisumador: semisumador PORT MAP(r_xor, c_in, s, r_and_2);
	or_cout: or2 PORT MAP(r_and_1, r_and_2, c_out);
END estructural;

Sesión 6/RCA.vhd
ENTITY RCA IS
	GENERIC (c: INTEGER:=4);
	PORT(x_in, y_in: IN BIT_VECTOR(c-1 downto 0); c_in: IN BIT; sal: OUT BIT_VECTOR(c-1 downto 0); c_out: OUT BIT);
END RCA;

ARCHITECTURE estructural OF RCA IS
	COMPONENT sumador
		PORT (x, y, c_in: IN BIT; s, c_out:OUT BIT);
	END COMPONENT;
	SIGNAL c_inside: BIT_VECTOR(c-1 downto 0);
BEGIN
	G: FOR i IN 0 TO c-1 GENERATE
		lsb: IF i = 0 GENERATE
			primero: sumador PORT MAP(x_in(0), y_in(0), c_in, sal(0), c_inside(0));
		END GENERATE lsb;
		
		siguientes: IF i > 0 AND i < c-1 GENERATE
			intermedios: sumador PORT MAP(x_in(i), y_in(i), c_inside(i-1), sal(i), c_inside(i));
		END GENERATE siguientes;
		
		msb: IF i = c-1 GENERATE
			ultimos: sumador PORT MAP(x_in(i), y_in(i), c_inside(i-1), sal(i), c_out);
		END GENERATE msb;
	END GENERATE G;
END estructural;

Sesión 6/Bloque_CSK.vhd
ENTITY Bloque_CSK IS
	GENERIC (c: INTEGER:=4);
	PORT(x_in, y_in: IN BIT_VECTOR(c-1 downto 0); c_in: IN BIT; sal: OUT BIT_VECTOR(c-1 downto 0); c_out: OUT BIT);
END ENTITY;

ARCHITECTURE estructural OF Bloque_CSK IS

COMPONENT RCA IS
	GENERIC (c: INTEGER:=4);
	PORT(x_in, y_in: IN BIT_VECTOR(c-1 downto 0); c_in: IN BIT; sal: OUT BIT_VECTOR(c-1 downto 0); c_out: OUT BIT);
END COMPONENT;
COMPONENT Bloque_P IS
	GENERIC (c: INTEGER:=4);
	PORT(x_in, y_in: IN BIT_VECTOR(c-1 downto 0); P: OUT BIT);
END COMPONENT;
COMPONENT and2 IS
	GENERIC (retardo: TIME:= 1 ns);
	PORT (e1, e2: IN BIT; sal: OUT BIT);
END COMPONENT;
COMPONENT or2 IS
	GENERIC (retardo: TIME:= 1 ns);
	PORT (e1, e2: IN BIT; sal: OUT BIT);
END COMPONENT;
SIGNAL P, c_out_aux, and_aux: BIT;
BEGIN

	sumador: RCA PORT MAP(x_in, y_in, c_in, sal, c_out_aux);
	propagacion: Bloque_P PORT MAP(x_in, y_in, P);
	and_cout: and2 PORT MAP(P, c_in, and_aux);
	or_cout: or2 PORT MAP(and_aux, c_out_aux, c_out);

END estructural;

Sesión 6/CSK.vhd
ENTITY CSK IS
	GENERIC (n: INTEGER:=16);
	PORT(x_in, y_in: IN BIT_VECTOR(n-1 downto 0); c_in: IN BIT; sal: OUT BIT_VECTOR(n-1 downto 0); c_out: OUT BIT);
END ENTITY;

ARCHITECTURE estructural OF CSK IS

COMPONENT Bloque_CSK
	GENERIC (c: INTEGER:=4);
	PORT(x_in, y_in: IN BIT_VECTOR(c-1 downto 0); c_in: IN BIT; sal: OUT BIT_VECTOR(c-1 downto 0); c_out: OUT BIT);
END COMPONENT;
COMPONENT RCA
	GENERIC (c: INTEGER:=4);
	PORT(x_in, y_in: IN BIT_VECTOR(c-1 downto 0); c_in: IN BIT; sal: OUT BIT_VECTOR(c-1 downto 0); c_out: OUT BIT);
END COMPONENT;

CONSTANT c: integer:=4;
SIGNAL c_aux: BIT_VECTOR ((n/4)-1 DOWNTO 0);

BEGIN

	primeros_bits: RCA PORT MAP(x_in(3 DOWNTO 0), y_in(3 DOWNTO 0), c_in, sal(3 DOWNTO 0), c_aux(0));
	G: FOR i IN 1 TO (n/4)-1 GENERATE
		siguientes: IF i < (n/4)-1 GENERATE
			intermedios: Bloque_CSK PORT MAP(x_in((i+1)*c-1 DOWNTO i*c), y_in((i+1)*c-1 DOWNTO i*c), c_aux(i-1), sal((i+1)*c-1 DOWNTO i*c), c_aux(i));
		END GENERATE siguientes;
		msb: IF i = c-1 GENERATE
			ultimos: Bloque_CSK PORT MAP(x_in((i+1)*c-1 DOWNTO i*c), y_in((i+1)*c-1 DOWNTO i*c), c_aux(i-1), sal((i+1)*c-1 DOWNTO i*c), c_out);
			END GENERATE msb;
	END GENERATE G;
END estructural;

Sesión 6/tb_CSK.vhd
ENTITY tb_CSK IS
END tb_CSK;

ARCHITECTURE estructural OF tb_CSK IS
	COMPONENT CSK
		GENERIC (n: INTEGER:=4);
		PORT(x_in, y_in: IN BIT_VECTOR(n-1 downto 0);
		     c_in: IN BIT;
		     sal: OUT BIT_VECTOR(n-1 downto 0);
		     c_out: OUT BIT);
	END COMPONENT;

	FOR componente: CSK USE ENTITY WORK.CSK(estructural);
	
	CONSTANT TAMANO_PALABRA: integer := 4;
	CONSTANT TAMANO_PALABRA_RCA: INTEGER := 2;
	
	SIGNAL a, b, r: BIT_VECTOR(TAMANO_PALABRA-1 downto 0);
	SIGNAL cin, cout, marca: BIT;
	
BEGIN
	
	componente: CSK GENERIC MAP (TAMANO_PALABRA) PORT MAP (A, B, Cin, R, Cout);
	
	PROCESS
	VARIABLE valor, limite, cuenta_carry, sol: INTEGER;
	BEGIN
		
		limite:= 2**TAMANO_PALABRA-1;
		
		FOR i IN 0 TO limite LOOP
			valor:=i;
			
			FOR k IN B'REVERSE_RANGE LOOP
				A(k)<=BIT'VAL(valor REM 2);--cambiamos A
				valor:=valor/2;
			END LOOP;
			
			FOR j IN 0 TO limite LOOP
				valor:=j;
				
				FOR k IN B'REVERSE_RANGE LOOP
					B(k)<=BIT'VAL(valor REM 2);--cambiamos B
					valor:=valor/2;
				END LOOP;
				FOR carry IN 0 TO 1 LOOP
					cin<=BIT'VAL(carry REM 2);
					WAIT FOR 30 ns;
				END LOOP;
			END LOOP;
		END LOOP;
	WAIT;
	END PROCESS;
END estructural;

Sesión 6/cronograma.vcd
$date
  Mon Feb  1 00:02:29 2021
$end
$version
  GHDL v0
$end
$timescale
  1 fs
$end
$scope module standard $end
$upscope $end
$scope module tb_csk $end
$var reg 4 ! a[3:0] $end
$var reg 4 " b[3:0] $end
$var reg 4 # r[3:0] $end
$var reg 1 $ cin $end
$var reg 1 % cout $end
$var reg 1 & marca $end
$scope module componente $end
$var reg 4 ' x_in[3:0] $end
$var reg 4 ( y_in[3:0] $end
$var reg 1 ) c_in $end
$var reg 4 * sal[3:0] $end
$var reg 1 + c_out $end
$var reg 1 , c_aux[0:0] $end
$scope module primeros_bits $end
$var reg 4 - x_in[3:0] $end
$var reg 4 . y_in[3:0] $end
$var reg 1 / c_in $end
$var reg 4 0 sal[3:0] $end
$var reg 1 1 c_out $end
$var reg 4 2 c_inside[3:0] $end
$scope module g(0) $end
$scope module lsb $end
$scope module primero $end
$var reg 1 3 x $end
$var reg 1 4 y $end
$var reg 1 5 c_in $end
$var reg 1 6 s $end
$var reg 1 7 c_out $end
$var reg 1 8 r_xor $end
$var reg 1 9 r_and_1 $end
$var reg 1 : r_and_2 $end
$scope module primer_semisumador $end
$var reg 1 ; x $end
$var reg 1 < y $end
$var reg 1 = r_xor $end
$var reg 1 > r_and $end
$scope module xor_n $end
$var reg 1 ? e1 $end
$var reg 1 @ e2 $end
$var reg 1 A sal $end
$upscope $end
$scope module and_n $end
$var reg 1 B e1 $end
$var reg 1 C e2 $end
$var reg 1 D sal $end
$upscope $end
$upscope $end
$scope module segundo_semisumador $end
$var reg 1 E x $end
$var reg 1 F y $end
$var reg 1 G r_xor $end
$var reg 1 H r_and $end
$scope module xor_n $end
$var reg 1 I e1 $end
$var reg 1 J e2 $end
$var reg 1 K sal $end
$upscope $end
$scope module and_n $end
$var reg 1 L e1 $end
$var reg 1 M e2 $end
$var reg 1 N sal $end
$upscope $end
$upscope $end
$scope module or_cout $end
$var reg 1 O e1 $end
$var reg 1 P e2 $end
$var reg 1 Q sal $end
$upscope $end
$upscope $end
$upscope $end
$upscope $end
$scope module g(1) $end
$scope module siguientes $end
$scope module intermedios $end
$var reg 1 R x $end
$var reg 1 S y $end
$var reg 1 T c_in $end
$var reg 1 U s $end
$var reg 1 V c_out $end
$var reg 1 W r_xor $end
$var reg 1 X r_and_1 $end
$var reg 1 Y r_and_2 $end
$scope module primer_semisumador $end
$var reg 1 Z x $end
$var reg 1 [ y $end
$var reg 1 \ r_xor $end
$var reg 1 ] r_and $end
$scope module xor_n $end
$var reg 1 ^ e1 $end
$var reg 1 _ e2 $end
$var reg 1 ` sal $end
$upscope $end
$scope module and_n $end
$var reg 1 a e1 $end
$var reg 1 b e2 $end
$var reg 1 c sal $end
$upscope $end
$upscope $end
$scope module segundo_semisumador $end
$var reg 1 d x $end
$var reg 1 e y $end
$var reg 1 f r_xor $end
$var reg 1 g r_and $end
$scope module xor_n $end
$var reg 1 h e1 $end
$var reg 1 i e2 $end
$var reg 1 j sal $end
$upscope $end
$scope module and_n $end
$var reg 1 k e1 $end
$var reg 1 l e2 $end
$var reg 1 m sal $end
$upscope $end
$upscope $end
$scope module or_cout $end
$var reg 1 n e1 $end
$var reg 1 o e2 $end
$var reg 1 p sal $end
$upscope $end
$upscope $end
$upscope $end
$upscope $end
$scope module g(2) $end
$scope module siguientes $end
$scope module intermedios $end
$var reg 1 q x $end
$var reg 1 r y $end
$var reg 1 s c_in $end
$var reg 1 t s $end
$var reg 1 u c_out $end
$var reg 1 v r_xor $end
$var reg 1 w r_and_1 $end
$var reg 1 x r_and_2 $end
$scope module primer_semisumador $end
$var reg 1 y x $end
$var reg 1 z y $end
$var reg 1 { r_xor $end
$var reg 1 | r_and $end
$scope module xor_n $end
$var reg 1 } e1 $end
$var reg 1 !" e2 $end
$var reg 1 "" sal $end
$upscope $end
$scope module and_n $end
$var reg 1 #" e1 $end
$var reg 1 $" e2 $end
$var reg 1 %" sal $end
$upscope $end
$upscope $end
$scope module segundo_semisumador $end
$var reg 1 &" x $end
$var reg 1 '" y $end
$var reg 1 (" r_xor $end
$var reg 1 )" r_and $end
$scope module xor_n $end
$var reg 1 *" e1 $end
$var reg 1 +" e2 $end
$var reg 1 ," sal $end
$upscope $end
$scope module and_n $end
$var reg 1 -" e1 $end
$var reg 1 ." e2 $end
$var reg 1 /" sal $end
$upscope $end
$upscope $end
$scope module or_cout $end
$var reg 1 0" e1 $end
$var reg 1 1" e2 $end
$var reg 1 2" sal $end
$upscope $end
$upscope $end
$upscope $end
$upscope $end
$scope module g(3) $end
$scope module msb $end
$scope module ultimos $end
$var reg 1 3" x $end
$var reg 1 4" y $end
$var reg 1 5" c_in $end
$var reg 1 6" s $end
$var reg 1 7" c_out $end
$var reg 1 8" r_xor $end
$var reg 1 9" r_and_1 $end
$var reg 1 :" r_and_2 $end
$scope module primer_semisumador $end
$var reg 1 ;" x $end
$var reg 1 <" y $end
$var reg 1 =" r_xor $end
$var reg 1 >" r_and $end
$scope module xor_n $end
$var reg 1 ?" e1 $end
$var reg 1 @" e2 $end
$var reg 1 A" sal $end
$upscope $end
$scope module and_n $end
$var reg 1 B" e1 $end
$var reg 1 C" e2 $end
$var reg 1 D" sal $end
$upscope $end
$upscope $end
$scope module segundo_semisumador $end
$var reg 1 E" x $end
$var reg 1 F" y $end
$var reg 1 G" r_xor $end
$var reg 1 H" r_and $end
$scope module xor_n $end
$var reg 1 I" e1 $end
$var reg 1 J" e2 $end
$var reg 1 K" sal $end
$upscope $end
$scope module and_n $end
$var reg 1 L" e1 $end
$var reg 1 M" e2 $end
$var reg 1 N" sal $end
$upscope $end
$upscope $end
$scope module or_cout $end
$var reg 1 O" e1 $end
$var reg 1 P" e2 $end
$var reg 1 Q" sal $end
$upscope $end
$upscope $end
$upscope $end
$upscope $end
$upscope $end
$upscope $end
$upscope $end
$enddefinitions $end
#0
b0000 !
b0000 "
b0000 #
0$
0%
0&
b0000 '
b0000 (
0)
b0000 *
0+
b0 ,
b0000 -
b0000 .
0/
b0000 0
01
b0000 2
03
04
05
06
07
08
09
0:
0;
0<
0=
0>
0?
0@
0A
0B
0C
0D
0E
0F
0G
0H
0I
0J
0K
0L
0M
0N
0O
0P
0Q
0R
0S
0T
0U
0V
0W
0X
0Y
0Z
0[
0\
0]
0^
0_
0`
0a
0b
0c
0d
0e
0f
0g
0h
0i
0j
0k
0l
0m
0n
0o
0p
0q
0r
0s
0t
0u
0v
0w
0x
0y
0z
0{
0|
0}
0!"
0""
0#"
0$"
0%"
0&"
0'"
0("
0)"
0*"
0+"
0,"
0-"
0."
0/"
00"
01"
02"
03"
04"
05"
06"
07"
08"
09"
0:"
0;"
0<"
0="
0>"
0?"
0@"
0A"
0B"
0C"
0D"
0E"
0F"
0G"
0H"
0I"
0J"
0K"
0L"
0M"
0N"
0O"
0P"
0Q"
#1000000
01
07
0>
0D
0H
0N
0Q
0V
0]
0c
0g
0m
0p
0u
0|
0%"
0)"
0/"
02"
07"
0>"
0D"
0H"
0N"
0Q"
#3000000
b0000 *
b0000 0
06
0=
0A
0G
0K
0U
0\
0`
0f
0j
0t
0{
0""
0("
0,"
06"
0="
0A"
0G"
0K"
#30000000
1$
1)
1/
15
1F
1J
1M
#31000000
0H
0N
#33000000
b0001 #
b0001 *
b0001 0
16
1G
1K
#60000000
b0001 "
0$
b0001 (
0)
b0001 .
0/
14
05
1<
1@
1C
0F
0J
0M
#61000000
0>
0D
0H
0N
#63000000
b0000 #
b0000 *
b0000 0
06
18
1=
1A
1E
0G
1I
0K
1L
#64000000
0H
0N
#66000000
b0001 #
b0001 *
b0001 0
16
1G
1K
#90000000
1$
1)
1/
15
1F
1J
1M
#91000000
1:
1H
1N
1P
#92000000
b0001 2
17
1Q
1T
1e
1i
1l
#93000000
b0000 #
b0000 *
b0000 0
06
0G
0K
0g
0m
#95000000
b0010 #
b0010 *
b0010 0
1U
1f
1j
#120000000
b0010 "
0$
b0010 (
0)
b0010 .
0/
04
05
0<
0@
0C
0F
0J
0M
1S
1[
1_
1b
#121000000
0:
0>
0D
0H
0N
0P
0]
0c
#122000000
b0000 2
07
0Q
0T
0e
0i
0l
#123000000
b0011 #
b0011 *
b0011 0
16
08
0=
0A
0E
1G
0I
1K
0L
1W
1\
1`
1d
0g
1h
1k
0m
#124000000
0H
0N
0g
0m
#126000000
b0010 #
b0010 *
b0010 0
06
0G
0K
1U
1f
1j
#150000000
1$
1)
1/
15
1F
1J
1M
#151000000
0H
0N
#153000000
b0011 #
b0011 *
b0011 0
16
1G
1K
#180000000
b0011 "
0$
b0011 (
0)
b0011 .
0/
14
05
1<
1@
1C
0F
0J
0M
#181000000
0>
0D
0H
0N
#183000000
b0010 #
b0010 *
b0010 0
06
18
1=
1A
1E
0G
1I
0K
1L
#184000000
0H
0N
#186000000
b0011 #
b0011 *
b0011 0
16
1G
1K
#210000000
1$
1)
1/
15
1F
1J
1M
#211000000
1:
1H
1N
1P
#212000000
b0001 2
17
1Q
1T
1e
1i
1l
#213000000
b0010 #
b0010 *
b0010 0
06
0G
0K
1Y
1g
1m
1o
#214000000
b0011 2
1V
1p
1s
1'"
1+"
1."
#215000000
b0000 #
b0000 *
b0000 0
0U
0f
0j
0)"
0/"
#217000000
b0100 #
b0100 *
b0100 0
1t
1("
1,"
#240000000
b0100 "
0$
b0100 (
0)
b0100 .
0/
04
05
0<
0@
0C
0F
0J
0M
0S
0[
0_
0b
1r
1z
1!"
1$"
#241000000
0:
0>
0D
0H
0N
0P
0]
0c
0|
0%"
#242000000
b0010 2
07
0Q
0T
0e
0i
0l
#243000000
b0101 #
b0101 *
b0101 0
16
08
0=
0A
0E
1G
0I
1K
0L
0W
0Y
0\
0`
0d
0g
0h
0k
0m
0o
1v
1{
1""
1&"
1*"
1-"
#244000000
b0000 2
0H
0N
0V
0g
0m
0p
0s
1x
0'"
1)"
0+"
0."
1/"
11"
#245000000
b0100 2
1u
0x
0)"
0/"
01"
12"
15"
1F"
1J"
1M"
#246000000
b0100 #
b0100 *
b0100 0
b0000 2
06
0G
0K
0U
0f
0j
0u
02"
05"
0F"
0H"
0J"
0M"
0N"
#247000000
b0100 *
b0100 0
1t
1("
1,"
0H"
0N"
#249000000
b0100 *
b0100 0
06"
0G"
0K"
#270000000
1$
1)
1/
15
1F
1J
1M
#271000000
0H
0N
#273000000
b0101 #
b0101 *
b0101 0
16
1G
1K
#300000000
b0101 "
0$
b0101 (
0)
b0101 .
0/
14
05
1<
1@
1C
0F
0J
0M
#301000000
0>
0D
0H
0N
#303000000
b0100 #
b0100 *
b0100 0
06
18
1=
1A
1E
0G
1I
0K
1L
#304000000
0H
0N
#306000000
b0101 #
b0101 *
b0101 0
16
1G
1K
#330000000
1$
1)
1/
15
1F
1J
1M
#331000000
1:
1H
1N
1P
#332000000
b0001 2
17
1Q
1T
1e
1i
1l
#333000000
b0100 #
b0100 *
b0100 0
06
0G
0K
0g
0m
#335000000
b0110 #
b0110 *
b0110 0
1U
1f
1j
#360000000
b0110 "
0$
b0110 (
0)
b0110 .
0/
04
05
0<
0@
0C
0F
0J
0M
1S
1[
1_
1b
#361000000
0:
0>
0D
0H
0N
0P
0]
0c
#362000000
b0000 2
07
0Q
0T
0e
0i
0l
#363000000
b0111 #
b0111 *
b0111 0
16
08
0=
0A
0E
1G
0I
1K
0L
1W
1\
1`
1d
0g
1h
1k
0m
#364000000
0H
0N
0g
0m
#366000000
b0110 #
b0110 *
b0110 0
06
0G
0K
1U
1f
1j
#390000000
1$
1)
1/
15
1F
1J
1M
#391000000
0H
0N
#393000000
b0111 #
b0111 *
b0111 0
16
1G
1K
#420000000
b0111 "
0$
b0111 (
0)
b0111 .
0/
14
05
1<
1@
1C
0F
0J
0M
#421000000
0>
0D
0H
0N
#423000000
b0110 #
b0110 *
b0110 0
06
18
1=
1A
1E
0G
1I
0K
1L
#424000000
0H
0N
#426000000
b0111 #
b0111 *
b0111 0
16
1G
1K
#450000000
1$
1)
1/
15
1F
1J
1M
#451000000
1:
1H
1N
1P
#452000000
b0001 2
17
1Q
1T
1e
1i
1l
#453000000
b0110 #
b0110 *
b0110 0
06
0G
0K
1Y
1g
1m
1o
#454000000
b0011 2
1V
1p
1s
1'"
1+"
1."
#455000000
b0100 #
b0100 *
b0100 0
0U
0f
0j
1x
1)"
1/"
11"
#456000000
b0111 2
1u
12"
15"
1F"
1J"
1M"
#457000000
b0000 #
b0000 *
b0000 0
0t
0("
0,"
0H"
0N"
#459000000
b1000 #
b1000 *
b1000 0
16"
1G"
1K"
#480000000
b1000 "
0$
b1000 (
0)
b1000 .
0/
04
05
0<
0@
0C
0F
0J
0M
0S
0[
0_
0b
0r
0z
0!"
0$"
14"
1<"
1@"
1C"
#481000000
0:
0>
0D
0H
0N
0P
0]
0c
0|
0%"
0>"
0D"
#482000000
b0110 2
07
0Q
0T
0e
0i
0l
#483000000
b1001 #
b1001 *
b1001 0
16
08
0=
0A
0E
1G
0I
1K
0L
0W
0Y
0\
0`
0d
0g
0h
0k
0m
0o
0v
0{
0""
0&"
0*"
0-"
18"
1="
1A"
1E"
1I"
1L"
#484000000
b0100 2
0H
0N
0V
0g
0m
0p
0s
0x
0'"
0)"
0+"
0."
0/"
01"
1:"
1H"
1N"
1P"
#485000000
b1 ,
11
b0000 2
0u
0)"
0/"
02"
05"
17"
0F"
0J"
0M"
1Q"
#486000000
b1000 #
b1000 *
b1000 0
06
0G
0K
0U
0f
0j
0:"
0H"
0N"
0P"
#487000000
b1000 *
b0 ,
b1000 0
01
0t
0("
0,"
07"
0Q"
#488000000
b1000 *
b1000 0
16"
1G"
1K"
#510000000
1$
1)
1/
15
1F
1J
1M
#511000000
0H
0N
#513000000
b1001 #
b1001 *
b1001 0
16
1G
1K
#540000000
b1001 "
0$
b1001 (
0)
b1001 .
0/
14
05
1<
1@
1C
0F
0J
0M
#541000000
0>
0D
0H
0N
#543000000
b1000 #
b1000 *
b1000 0
06
18
1=
1A
1E
0G
1I
0K
1L
#544000000
0H
0N
#546000000
b1001 #
b1001 *
b1001 0
16
1G
1K
#570000000
1$
1)
1/
15
1F
1J
1M
#571000000
1:
1H
1N
1P
#572000000
b0001 2
17
1Q
1T
1e
1i
1l
#573000000
b1000 #
b1000 *
b1000 0
06
0G
0K
0g
0m
#575000000
b1010 #
b1010 *
b1010 0
1U
1f
1j
#600000000
b1010 "
0$
b1010 (
0)
b1010 .
0/
04
05
0<
0@
0C
0F
0J
0M
1S
1[
1_
1b
#601000000
0:
0>
0D
0H
0N
0P
0]
0c
#602000000
b0000 2
07
0Q
0T
0e
0i
0l
#603000000
b1011 #
b1011 *
b1011 0
16
08
0=
0A
0E
1G
0I
1K
0L
1W
1\
1`
1d
0g
1h
1k
0m
#604000000
0H
0N
0g
0m
#606000000
b1010 #
b1010 *
b1010 0
06
0G
0K
1U
1f
1j
#630000000
1$
1)
1/
15
1F
1J
1M
#631000000
0H
0N
#633000000
b1011 #
b1011 *
b1011 0
16
1G
1K
#660000000
b1011 "
0$
b1011 (
0)
b1011 .
0/
14
05
1<
1@
1C
0F
0J
0M
#661000000
0>
0D
0H
0N
#663000000
b1010 #
b1010 *
b1010 0
06
18
1=
1A
1E
0G
1I
0K
1L
#664000000
0H
0N
#666000000
b1011 #
b1011 *
b1011 0
16
1G
1K
#690000000
1$
1)
1/
15
1F
1J
1M
#691000000
1:
1H
1N
1P
#692000000
b0001 2
17
1Q
1T
1e
1i
1l
#693000000
b1010 #
b1010 *
b1010 0
06
0G
0K
1Y
1g
1m
1o
#694000000
b0011 2
1V
1p
1s
1'"
1+"
1."
#695000000
b1000 #
b1000 *
b1000 0
0U
0f
0j
0)"
0/"
#697000000
b1100 #
b1100 *
b1100 0
1t
1("
1,"
#720000000
b1100 "
0$
b1100 (
0)
b1100 .
0/
04
05
0<
0@
0C
0F
0J
0M
0S
0[
0_
0b
1r
1z
1!"
1$"
#721000000
0:
0>
0D
0H
0N
0P
0]
0c
0|
0%"
#722000000
b0010 2
07
0Q
0T
0e
0i
0l
#723000000
b1101 #
b1101 *
b1101 0
16
08
0=
0A
0E
1G
0I
1K
0L
0W
0Y
0\
0`
0d
0g
0h
0k
0m
0o
1v
1{
1""
1&"
1*"
1-"
#724000000
b0000 2
0H
0N
0V
0g
0m
0p
0s
1x
0'"
1)"
0+"
0."
1/"
11"
#725000000
b0100 2
1u
0x
0)"
0/"
01"
12"
15"
1F"
1J"
1M"
#726000000
b1100 #
b1100 *
b1100 0
b0000 2
06
0G
0K
0U
0f
0j
0u
02"
05"
1:"
0F"
1H"
0J"
0M"
1N"
1P"
#727000000
b1100 *
b1 ,
b1100 0
11
1t
1("
1,"
17"
0:"
0H"
0N"
0P"
1Q"
#728000000
b0 ,
01
07"
0Q"
#729000000
b1100 *
b1100 0
16"
1G"
1K"
#750000000
1$
1)
1/
15
1F
1J
1M
#751000000
0H
0N
#753000000
b1101 #
b1101 *
b1101 0
16
1G
1K
#780000000
b1101 "
0$
b1101 (
0)
b1101 .
0/
14
05
1<
1@
1C
0F
0J
0M
#781000000
0>
0D
0H
0N
#783000000
b1100 #
b1100 *
b1100 0
06
18
1=
1A
1E
0G
1I
0K
1L
#784000000
0H
0N
#786000000
b1101 #
b1101 *
b1101 0
16
1G
1K
#810000000
1$
1)
1/
15
1F
1J
1M
#811000000
1:
1H
1N
1P
#812000000
b0001 2
17
1Q
1T
1e
1i
1l
#813000000
b1100 #
b1100 *
b1100 0
06
0G
0K
0g
0m
#815000000
b1110 #
b1110 *
b1110 0
1U
1f
1j
#840000000
b1110 "
0$
b1110 (
0)
b1110 .
0/
04
05
0<
0@
0C
0F
0J
0M
1S
1[
1_
1b
#841000000
0:
0>
0D
0H
0N
0P
0]
0c
#842000000
b0000 2
07
0Q
0T
0e
0i
0l
#843000000
b1111 #
b1111 *
b1111 0
16
08
0=
0A
0E
1G
0I
1K
0L
1W
1\
1`
1d
0g
1h
1k
0m
#844000000
0H
0N
0g
0m
#846000000
b1110 #
b1110 *
b1110 0
06
0G
0K
1U
1f
1j
#870000000
1$
1)
1/
15
1F
1J
1M
#871000000
0H
0N
#873000000
b1111 #
b1111 *
b1111 0
16
1G
1K
#900000000
b1111 "
0$
b1111 (
0)
b1111 .
0/
14
05
1<
1@
1C
0F
0J
0M
#901000000
0>
0D
0H
0N
#903000000
b1110 #
b1110 *
b1110 0
06
18
1=
1A
1E
0G
1I
0K
1L
#904000000
0H
0N
#906000000
b1111 #
b1111 *
b1111 0
16
1G
1K
#930000000
1$
1)
1/
15
1F
1J
1M
#931000000
1:
1H
1N
1P
#932000000
b0001 2
17
1Q
1T
1e
1i
1l
#933000000
b1110 #
b1110 *
b1110 0
06
0G
0K
1Y
1g
1m
1o
#934000000
b0011 2
1V
1p
1s
1'"
1+"
1."
#935000000
b1100 #
b1100 *
b1100 0
0U
0f
0j
1x
1)"
1/"
11"
#936000000
b0111 2
1u
12"
15"
1F"
1J"
1M"
#937000000
b1000 #
b1000 *
b1000 0
0t
0("
0,"
1:"
1H"
1N"
1P"
#938000000
b1 ,
11
17"
1Q"
#939000000
b0000 #
b0000 *
b0000 0
06"
0G"
0K"
#960000000
b0001 !
b0000 "
0$
b0001 '
b0000 (
0)
b0001 -
b0000 .
0/
13
04
05
1;
0<
1?
0@
1B
0C
0F
0J
0M
0S
0[
0_
0b
0r
0z
0!"
0$"
04"
0<"
0@"
0C"
#961000000
0:
0>
0D
0H
0N
0P
0]
0c
0|
0%"
0>"
0D"
#962000000
b0110 2
07
0Q
0T
0e
0i
0l
#963000000
b0001 #
b0001 *
b0001 0
16
1=
1A
1G
1K
0W
0Y
0\
0`
0d
0g
0h
0k
0m
0o
0v
0{
0""
0&"
0*"
0-"
08"
0="
0A"
0E"
0I"
0L"
#964000000
b0100 2
0V
0g
0m
0p
0s
0x
0'"
0)"
0+"
0."
0/"
01"
0:"
0H"
0N"
0P"
#965000000
b0 ,
01
b0000 2
0u
0)"
0/"
02"
05"
07"
0F"
0J"
0M"
0Q"
#966000000
b0001 *
b0001 0
0U
0f
0j
0H"
0N"
#967000000
b0001 *
b0001 0
0t
0("
0,"
#968000000
b0001 *
b0001 0
06"
0G"
0K"
#990000000
1$
1)
1/
15
1F
1J
1M
#991000000
1:
1H
1N
1P
#992000000
b0001 2
17
1Q
1T
1e
1i
1l
#993000000
b0000 #
b0000 *
b0000 0
06
0G
0K
0g
0m
#995000000
b0010 #
b0010 *
b0010 0
1U
1f
1j
#1020000000
b0001 "
0$
b0001 (
0)
b0001 .
0/
14
05
1<
1@
1C
0F
0J
0M
#1021000000
19
0:
1>
1D
0H
0N
1O
0P
#1022000000
17
1Q
#1023000000
b0011 #
b0011 *
b0011 0
16
08
0=
0A
0E
1G
0I
1K
0L
