Sesión 2/XOR/xor2.vhd
--puerta and de 2 entradas

ENTITY xor2 IS
	GENERIC (retardo: TIME:= 2 ns);
	PORT (e1, e2: IN BIT; sal: OUT BIT);
END xor2;

ARCHITECTURE comportamiento OF xor2 IS
BEGIN
	PROCESS (e1, e2)
	BEGIN
		sal <= e1 XOR e2 AFTER retardo;
	END PROCESS;
END comportamiento;

Sesión 2/Inversor condicional/inversor_condicional.vhd
ENTITY inversor_condicional IS
	GENERIC (n: INTEGER:=8);
	PORT (x, y: IN BIT_VECTOR(n-1 DOWNTO 0); r:OUT BIT_VECTOR(n-1 DOWNTO 0));
END inversor_condicional;

ARCHITECTURE estructural OF inversor_condicional IS
	COMPONENT xor2
		PORT (e1, e2: IN BIT; sal: OUT BIT);
	END COMPONENT;
BEGIN
	bateria: FOR i IN 0 TO n-1 GENERATE
		puertas: xor2 PORT MAP (x(i), y(i), r(i));
	END GENERATE;
END estructural;

Sesión 2/Inversor condicional/tb_inversor_condicional.vhd
ENTITY tb_inversor_condicional IS
END tb_inversor_condicional;

ARCHITECTURE estructural OF tb_inversor_condicional IS
	COMPONENT inversor_condicional
		GENERIC (n: INTEGER:=8);
		PORT (x, y: IN BIT_VECTOR(n-1 DOWNTO 0); r: OUT BIT_VECTOR(n-1 DOWNTO 0));
	END COMPONENT;
	
	FOR operador: inversor_condicional USE ENTITY WORK.inversor_condicional(estructural);
	
	CONSTANT TAMANO_PALABRA: integer := 2;
	
	SIGNAL A, B, C: BIT_VECTOR(TAMANO_PALABRA-1 DOWNTO 0);

BEGIN
	operador: inversor_condicional GENERIC MAP (TAMANO_PALABRA) PORT MAP(A, B, C); --B es la señal ENABLE
	
	PROCESS
	VARIABLE valor, limite, ENABLE: INTEGER;
	BEGIN
		limite:= 2**TAMANO_PALABRA-1;
		ENABLE:=1;
		
		FOR i IN 0 TO limite LOOP
			valor:=i;
			
			FOR k IN A'REVERSE_RANGE LOOP
				A(k)<=BIT'VAL(valor REM 2);
				valor:=valor/2;
			END LOOP;
			
			FOR j IN 0 TO limite LOOP
				valor:=j;
				
				FOR k IN B'REVERSE_RANGE LOOP
					B(k)<=BIT'VAL(ENABLE);
					valor:=valor/2;
				END LOOP;
				WAIT FOR 2 ns;
				
			END LOOP;
		END LOOP;
		
		
		WAIT FOR 2 ns;
		
		ENABLE:=0;
		
		FOR i IN 0 TO limite LOOP
			valor:=i;
			
			FOR k IN A'REVERSE_RANGE LOOP
				A(k)<=BIT'VAL(valor REM 2);
				valor:=valor/2;
			END LOOP;
			
			FOR j IN 0 TO limite LOOP
				valor:=j;
				
				FOR k IN B'REVERSE_RANGE LOOP
					B(k)<=BIT'VAL(ENABLE);
					valor:=valor/2;
				END LOOP;
				WAIT FOR 2 ns;
				
			END LOOP;
		END LOOP;
		
		
		WAIT FOR 2 ns;
		WAIT;
		
	END PROCESS;
END estructural;

Sesión 2/Inversor condicional/cronograma.vcd
$date
  Fri Oct 30 12:56:11 2020
$end
$version
  GHDL v0
$end
$timescale
  1 fs
$end
$scope module standard $end
$upscope $end
$scope module tb_inversor_condicional $end
$var reg 2 ! a[1:0] $end
$var reg 2 " b[1:0] $end
$var reg 2 # c[1:0] $end
$scope module operador $end
$var reg 2 $ x[1:0] $end
$var reg 2 % y[1:0] $end
$var reg 2 & r[1:0] $end
$scope module bateria(0) $end
$scope module puertas $end
$var reg 1 ' e1 $end
$var reg 1 ( e2 $end
$var reg 1 ) sal $end
$upscope $end
$upscope $end
$scope module bateria(1) $end
$scope module puertas $end
$var reg 1 * e1 $end
$var reg 1 + e2 $end
$var reg 1 , sal $end
$upscope $end
$upscope $end
$upscope $end
$upscope $end
$enddefinitions $end
#0
b00 !
b11 "
b00 #
b00 $
b11 %
b00 &
0'
1(
0)
0*
1+
0,
#2000000
b11 #
b11 &
1)
1,
#4000000
#6000000
#8000000
b01 !
b01 $
1'
#10000000
b10 #
b10 &
0)
#12000000
#14000000
#16000000
b10 !
b10 $
0'
1*
#18000000
b01 #
b01 &
1)
0,
#20000000
#22000000
#24000000
b11 !
b11 $
1'
#26000000
b00 #
b00 &
0)
#28000000
#30000000
#32000000
#34000000
b00 !
b00 "
b00 $
b00 %
0'
0(
0*
0+
#36000000
b00 &
0)
0,
#38000000
#40000000
#42000000
b01 !
b01 $
1'
#44000000
b01 #
b01 &
1)
#46000000
#48000000
#50000000
b10 !
b10 $
0'
1*
#52000000
b10 #
b10 &
0)
1,
#54000000
#56000000
#58000000
b11 !
b11 $
1'
#60000000
b11 #
b11 &
1)
