Sesión 4/Semisumadores/or2.vhd
--puerta and de 2 entradas

ENTITY or2 IS
	GENERIC (retardo: TIME:= 1 ns);
	PORT (e1, e2: IN BIT; sal: OUT BIT);
END or2;

ARCHITECTURE comportamiento OF or2 IS
BEGIN
	PROCESS (e1, e2)
	BEGIN
		sal <= e1 OR e2 AFTER retardo;
	END PROCESS;
END comportamiento;

Sesión 4/Semisumadores/and2.vhd
--puerta and de 2 entradas

ENTITY and2 IS
	GENERIC (retardo: TIME:= 1 ns);
	PORT (e1, e2: IN BIT; sal: OUT BIT);
END and2;

ARCHITECTURE comportamiento OF and2 IS
BEGIN
	PROCESS (e1, e2)
	BEGIN
		sal <= e1 AND e2 AFTER retardo;
	END PROCESS;
END comportamiento;

Sesión 4/Semisumadores/xor2.vhd
--puerta and de 2 entradas

ENTITY xor2 IS
	GENERIC (retardo: TIME:= 1 ns);
	PORT (e1, e2: IN BIT; sal: OUT BIT);
END xor2;

ARCHITECTURE comportamiento OF xor2 IS
BEGIN
	PROCESS (e1, e2)
	BEGIN
		sal <= e1 XOR e2 AFTER retardo;
	END PROCESS;
END comportamiento;

Sesión 6/semisumador.vhd
ENTITY semisumador IS
	PORT (x, y: IN BIT; r_xor, r_and:OUT BIT);
END semisumador;

ARCHITECTURE estructural OF semisumador IS
	COMPONENT xor2
		PORT (e1, e2: IN BIT; sal:OUT BIT);
	END COMPONENT;
	COMPONENT and2
		PORT (e1, e2: IN BIT; sal:OUT BIT);
	END COMPONENT;
BEGIN
		xor_n: xor2 PORT MAP (x, y, r_xor);
		and_n: and2 PORT MAP (x, y, r_and);
END estructural;

Sesión 6/sumador.vhd
ENTITY sumador IS
	PORT (x, y, c_in: IN BIT; s, c_out:OUT BIT);
END sumador;

ARCHITECTURE estructural OF sumador IS
	COMPONENT semisumador
		PORT (x, y: IN BIT; r_xor, r_and:OUT BIT);
	END COMPONENT;
	COMPONENT or2
		PORT (e1, e2: IN BIT; sal:OUT BIT);
	END COMPONENT;
	SIGNAL r_xor, r_and_1, r_and_2: BIT;
BEGIN
	primer_semisumador: semisumador PORT MAP(x, y, r_xor, r_and_1);
	segundo_semisumador: semisumador PORT MAP(r_xor, c_in, s, r_and_2);
	or_cout: or2 PORT MAP(r_and_1, r_and_2, c_out);
END estructural;

Sesión 4/Semisumadores/RCA.vhd
ENTITY RCA IS
	GENERIC (n: INTEGER:=8);
	PORT(x_in, y_in: IN BIT_VECTOR(n-1 downto 0); c_in: IN BIT; sal: OUT BIT_VECTOR(n-1 downto 0); c_out: OUT BIT);
END RCA;

ARCHITECTURE estructural OF RCA IS
	COMPONENT sumador
		PORT (x, y, c_in: IN BIT; s, c_out:OUT BIT);
	END COMPONENT;
	
	SIGNAL c_inside: BIT_VECTOR(n-1 downto 0);
BEGIN
	G: FOR i IN 0 TO n-1 GENERATE
		lsb: IF i = 0 GENERATE
			primero: sumador PORT MAP(x_in(0), y_in(0), c_in, sal(0), c_inside(0));
		END GENERATE lsb;
		
		siguientes: IF i > 0 AND i < n-1 GENERATE
			intermedios: sumador PORT MAP(x_in(i), y_in(i), c_inside(i-1), sal(i), c_inside(i));
		END GENERATE siguientes;
		
		msb: IF i = n-1 GENERATE
			ultimos: sumador PORT MAP(x_in(i), y_in(i), c_inside(i-1), sal(i), c_out);
		END GENERATE msb;
	END GENERATE G;
END estructural;

Sesión 4/Semisumadores/tb_RCA.vhd
ENTITY tb_RCA IS
END tb_RCA;

ARCHITECTURE estructural OF tb_RCA IS
	COMPONENT RCA
		GENERIC (n: INTEGER:=8);
		PORT(x_in, y_in: IN BIT_VECTOR(n-1 downto 0);
		     c_in: IN BIT;
		     sal: OUT BIT_VECTOR(n-1 downto 0);
		     c_out: OUT BIT);
	END COMPONENT;

	FOR componente: RCA USE ENTITY WORK.RCA(estructural);
	
	CONSTANT TAMANO_PALABRA: integer := 2;
	
	SIGNAL a, b, r: BIT_VECTOR(TAMANO_PALABRA-1 downto 0);
	SIGNAL cin, cout, marca: BIT;
	
BEGIN
	
	componente: RCA GENERIC MAP (TAMANO_PALABRA) PORT MAP (A, B, Cin, R, Cout);
	
	PROCESS
	VARIABLE valor, i, j, n: INTEGER;
	BEGIN
		
		valor:=0;
		i:=0;
		j:=0;
		n:=0;
		A<=(others=>'0');
		B<=(others=>'0');
		Cin<='0';
		marca<='0';
		WAIT FOR TAMANO_PALABRA*10 ns;
		A<=(others=>'1');
		Cin<='1';
		marca<='1';
		WAIT UNTIL Cout='1' AND R(TAMANO_PALABRA-1)='0';
		marca<='0';


		FOR k IN A'RANGE LOOP
			IF A(k)='1' THEN
				i:=i+2**k;
			END IF;
		END LOOP;
		FOR k IN B'RANGE LOOP
			IF B(k)='1' THEN
				j:=j+2**k;
			END IF;
		END LOOP;
		IF Cin='1' THEN
			valor:=valor+1;
			n:=1;
		ELSE
			n:=0;
		END IF;
		FOR k IN R'RANGE LOOP
			IF R(k)='1' THEN
				valor:=valor+2**k;
			END IF;
		END LOOP;
		
		IF Cout='1' THEN
			valor:=valor+2**TAMANO_PALABRA;
		END IF;
		
		ASSERT valor=i+j REPORT "resultado incorrecto" SEVERITY ERROR;
		WAIT FOR 2 ns;
		WAIT;

	END PROCESS;
END estructural;

Sesión 4/Semisumadores/cronograma.vcd
$date
  Thu Dec 10 11:14:17 2020
$end
$version
  GHDL v0
$end
$timescale
  1 fs
$end
$scope module standard $end
$upscope $end
$scope module tb_rca $end
$var reg 2 ! a[1:0] $end
$var reg 2 " b[1:0] $end
$var reg 2 # r[1:0] $end
$var reg 1 $ cin $end
$var reg 1 % cout $end
$var reg 1 & marca $end
$scope module componente $end
$var reg 2 ' x_in[1:0] $end
$var reg 2 ( y_in[1:0] $end
$var reg 1 ) c_in $end
$var reg 2 * sal[1:0] $end
$var reg 1 + c_out $end
$var reg 2 , c_inside[1:0] $end
$scope module g(0) $end
$scope module lsb $end
$scope module primero $end
$var reg 1 - x $end
$var reg 1 . y $end
$var reg 1 / c_in $end
$var reg 1 0 s $end
$var reg 1 1 c_out $end
$var reg 1 2 r_xor $end
$var reg 1 3 r_and_1 $end
$var reg 1 4 r_and_2 $end
$scope module primer_semisumador $end
$var reg 1 5 x $end
$var reg 1 6 y $end
$var reg 1 7 r_xor $end
$var reg 1 8 r_and $end
$scope module xor_n $end
$var reg 1 9 e1 $end
$var reg 1 : e2 $end
$var reg 1 ; sal $end
$upscope $end
$scope module and_n $end
$var reg 1 < e1 $end
$var reg 1 = e2 $end
$var reg 1 > sal $end
$upscope $end
$upscope $end
$scope module segundo_semisumador $end
$var reg 1 ? x $end
$var reg 1 @ y $end
$var reg 1 A r_xor $end
$var reg 1 B r_and $end
$scope module xor_n $end
$var reg 1 C e1 $end
$var reg 1 D e2 $end
$var reg 1 E sal $end
$upscope $end
$scope module and_n $end
$var reg 1 F e1 $end
$var reg 1 G e2 $end
$var reg 1 H sal $end
$upscope $end
$upscope $end
$scope module or_cout $end
$var reg 1 I e1 $end
$var reg 1 J e2 $end
$var reg 1 K sal $end
$upscope $end
$upscope $end
$upscope $end
$upscope $end
$scope module g(1) $end
$scope module msb $end
$scope module ultimos $end
$var reg 1 L x $end
$var reg 1 M y $end
$var reg 1 N c_in $end
$var reg 1 O s $end
$var reg 1 P c_out $end
$var reg 1 Q r_xor $end
$var reg 1 R r_and_1 $end
$var reg 1 S r_and_2 $end
$scope module primer_semisumador $end
$var reg 1 T x $end
$var reg 1 U y $end
$var reg 1 V r_xor $end
$var reg 1 W r_and $end
$scope module xor_n $end
$var reg 1 X e1 $end
$var reg 1 Y e2 $end
$var reg 1 Z sal $end
$upscope $end
$scope module and_n $end
$var reg 1 [ e1 $end
$var reg 1 \ e2 $end
$var reg 1 ] sal $end
$upscope $end
$upscope $end
$scope module segundo_semisumador $end
$var reg 1 ^ x $end
$var reg 1 _ y $end
$var reg 1 ` r_xor $end
$var reg 1 a r_and $end
$scope module xor_n $end
$var reg 1 b e1 $end
$var reg 1 c e2 $end
$var reg 1 d sal $end
$upscope $end
$scope module and_n $end
$var reg 1 e e1 $end
$var reg 1 f e2 $end
$var reg 1 g sal $end
$upscope $end
$upscope $end
$scope module or_cout $end
$var reg 1 h e1 $end
$var reg 1 i e2 $end
$var reg 1 j sal $end
$upscope $end
$upscope $end
$upscope $end
$upscope $end
$upscope $end
$upscope $end
$enddefinitions $end
#0
b00 !
b00 "
b00 #
0$
0%
0&
b00 '
b00 (
0)
b00 *
0+
b00 ,
0-
0.
0/
00
01
02
03
04
05
06
07
08
09
0:
0;
0<
0=
0>
0?
0@
0A
0B
0C
0D
0E
0F
0G
0H
0I
0J
0K
0L
0M
0N
0O
0P
0Q
0R
0S
0T
0U
0V
0W
0X
0Y
0Z
0[
0\
0]
0^
0_
0`
0a
0b
0c
0d
0e
0f
0g
0h
0i
0j
#1000000
b00 *
0+
00
01
07
08
0;
0>
0A
0B
0E
0H
0K
0O
0P
0V
0W
0Z
0]
0`
0a
0d
0g
0j
#20000000
b11 !
1$
1&
b11 '
1)
1-
1/
15
19
1<
1@
1D
1G
1L
1T
1X
1[
#21000000
b01 #
b01 *
10
12
17
08
1;
0>
1?
1A
0B
1C
1E
1F
0H
1Q
1V
0W
1Z
0]
1^
1b
1e
#22000000
b10 #
b10 *
00
14
0A
1B
0E
1H
1J
1O
1`
0a
1d
0g
#23000000
b01 ,
11
1K
1N
1_
1c
1f
#24000000
b00 #
b00 *
0O
1S
0`
1a
0d
1g
1i
#25000000
1%
0&
1+
1P
1j
