Sesión 7/Primer '1'/not2.vhd
ENTITY not2 IS
	GENERIC (retardo: TIME:= 1 ns);
	PORT (e: IN BIT; sal: OUT BIT);
END not2;

ARCHITECTURE comportamiento OF not2 IS
BEGIN
	PROCESS (e)
	BEGIN
		sal <= NOT e AFTER retardo;
	END PROCESS;
END comportamiento;

Sesión 2/NOT/op_not_n.vhd
ENTITY op_not_n IS
	GENERIC (n: INTEGER:=8);
	PORT (x: IN BIT_VECTOR(n-1 DOWNTO 0); s:OUT BIT_VECTOR(n-1 DOWNTO 0));
END op_not_n;

ARCHITECTURE estructural OF op_not_n IS
	COMPONENT not2
		PORT (e: IN BIT; sal: OUT BIT);
	END COMPONENT;
BEGIN
	bateria: FOR i IN 0 TO n-1 GENERATE
		puertas: not2 PORT MAP (x(i), s(i));
	END GENERATE;
END estructural;

Sesión 2/NOT/tb_op_not_n.vhd
ENTITY tb_op_not_n IS
END tb_op_not_n;

ARCHITECTURE estructural OF tb_op_not_n IS
	COMPONENT op_not_n
		GENERIC (n: INTEGER:=8);
		PORT (x: IN BIT_VECTOR(n-1 DOWNTO 0); s: OUT BIT_VECTOR(n-1 DOWNTO 0));
	END COMPONENT;
	
	FOR operador: op_not_n USE ENTITY WORK.op_not_n(estructural);
	
	CONSTANT TAMANO_PALABRA: integer := 2;
	
	SIGNAL A, B: BIT_VECTOR(TAMANO_PALABRA-1 DOWNTO 0);

BEGIN
	operador: op_not_n GENERIC MAP (TAMANO_PALABRA) PORT MAP(A, B);
	
	PROCESS
	VARIABLE valor, limite: INTEGER;
	BEGIN
		limite:= 2**TAMANO_PALABRA-1;
		
		FOR i IN 0 TO limite LOOP
			valor:=i;
			
			FOR k IN A'REVERSE_RANGE LOOP
				A(k)<=BIT'VAL(valor REM 2);
				valor:=valor/2;
			END LOOP;
				WAIT FOR 2 ns;
				
		END LOOP;
		
		WAIT FOR 2 ns;
		WAIT;
	END PROCESS;
END estructural;

Sesión 2/NOT/cronograma.vcd
$date
  Fri Oct 30 13:23:58 2020
$end
$version
  GHDL v0
$end
$timescale
  1 fs
$end
$scope module standard $end
$upscope $end
$scope module tb_op_not_n $end
$var reg 2 ! a[1:0] $end
$var reg 2 " b[1:0] $end
$scope module operador $end
$var reg 2 # x[1:0] $end
$var reg 2 $ s[1:0] $end
$scope module bateria(0) $end
$scope module puertas $end
$var reg 1 % e $end
$var reg 1 & sal $end
$upscope $end
$upscope $end
$scope module bateria(1) $end
$scope module puertas $end
$var reg 1 ' e $end
$var reg 1 ( sal $end
$upscope $end
$upscope $end
$upscope $end
$upscope $end
$enddefinitions $end
#0
b00 !
b00 "
b00 #
b00 $
0%
0&
0'
0(
#1000000
b11 "
b11 $
1&
1(
#2000000
b01 !
b01 #
1%
#3000000
b10 "
b10 $
0&
#4000000
b10 !
b10 #
0%
1'
#5000000
b01 "
b01 $
1&
0(
#6000000
b11 !
b11 #
1%
#7000000
b00 "
b00 $
0&
